{"Bladder, Urinary": {"male": {"observed": 61.0, "expected": 52.5, "sir": 116.2, "ci_low": 88.9, "ci_high": 149.3, "significant": true}, "female": {"observed": 21.0, "expected": 20.2, "sir": 104.0, "ci_low": 64.3, "ci_high": 158.9, "significant": true}, "combined": {"observed": 82.0, "expected": 72.7, "sir": 112.79229711141679, "ci_low": null, "ci_high": null, "significant": true}}, "Melanoma of Skin": {"male": {"observed": 25.0, "expected": 35.8, "sir": 69.9, "ci_low": 45.2, "ci_high": 103.2, "significant": true}, "female": {"observed": 14.0, "expected": 30.7, "sir": 45.6, "ci_low": 24.9, "ci_high": 76.6, "significant": true}, "combined": {"observed": 39.0, "expected": 66.5, "sir": 58.64661654135338, "ci_low": null, "ci_high": null, "significant": true}}, "Brain and Other Nervous System": {"male": {"observed": 15.0, "expected": 11.4, "sir": 132.0, "ci_low": 73.8, "ci_high": 217.8, "significant": true}, "female": {"observed": 13.0, "expected": 9.5, "sir": 136.8, "ci_low": 72.8, "ci_high": 233.9, "significant": true}, "combined": {"observed": 28.0, "expected": 20.9, "sir": 133.9712918660287, "ci_low": null, "ci_high": null, "significant": true}}, "Multiple Myeloma": {"male": {"observed": 9.0, "expected": 10.7, "sir": 83.8, "ci_low": 38.3, "ci_high": 159.1, "significant": true}, "female": {"observed": 4.0, "expected": 9.1, "sir": null, "ci_low": null, "ci_high": null, "significant": false}, "combined": {"observed": 13.0, "expected": 19.799999999999997, "sir": null, "ci_low": null, "ci_high": null, "significant": false}}, "Breast": {"male": {"observed": 2.0, "expected": 1.8, "sir": null, "ci_low": null, "ci_high": null, "significant": false}, "female": {"observed": 234.0, "expected": 221.2, "sir": 105.8, "ci_low": 92.7, "ci_high": 120.2, "significant": true}, "combined": {"observed": 236.0, "expected": 223.0, "sir": null, "ci_low": null, "ci_high": null, "significant": false}}, "Non-Hodgkin Lymphoma": {"male": {"observed": 26.0, "expected": 31.7, "sir": 82.0, "ci_low": 53.5, "ci_high": 120.1, "significant": true}, "female": {"observed": 32.0, "expected": 28.6, "sir": 111.8, "ci_low": 76.4, "ci_high": 157.8, "significant": true}, "combined": {"observed": 58.0, "expected": 60.3, "sir": 96.18573797678276, "ci_low": null, "ci_high": null, "significant": true}}, "Cervix Uteri": {"male": {"observed": 0, "expected": 0, "sir": null, "ci_low": null, "ci_high": null, "significant": false}, "female": {"observed": 9.0, "expected": 8.2, "sir": 109.7, "ci_low": 50.1, "ci_high": 208.3, "significant": true}, "combined": {"observed": 9.0, "expected": 8.2, "sir": null, "ci_low": null, "ci_high": null, "significant": false}}, "Oral Cavity & Pharynx": {"male": {"observed": 16.0, "expected": 25.4, "sir": 63.1, "ci_low": 36.0, "ci_high": 102.4, "significant": true}, "female": {"observed": 8.0, "expected": 11.9, "sir": 67.0, "ci_low": 28.9, "ci_high": 132.1, "significant": true}, "combined": {"observed": 24.0, "expected": 37.3, "sir": 64.34316353887401, "ci_low": null, "ci_high": null, "significant": true}}, "Colon / Rectum": {"male": {"observed": 60.0, "expected": 57.2, "sir": 104.8, "ci_low": 80.0, "ci_high": 134.9, "significant": true}, "female": {"observed": 56.0, "expected": 60.8, "sir": 92.1, "ci_low": 69.6, "ci_high": 119.6, "significant": true}, "combined": {"observed": 116.0, "expected": 118.0, "sir": 98.30508474576271, "ci_low": null, "ci_high": null, "significant": true}}, "Ovary": {"male": {"observed": 0, "expected": 0, "sir": null, "ci_low": null, "ci_high": null, "significant": false}, "female": {"observed": 18.0, "expected": 20.1, "sir": 89.4, "ci_low": 52.9, "ci_high": 141.3, "significant": true}, "combined": {"observed": 18.0, "expected": 20.1, "sir": null, "ci_low": null, "ci_high": null, "significant": false}}, "Esophagus": {"male": {"observed": 13.0, "expected": 14.1, "sir": 92.1, "ci_low": 49.0, "ci_high": 157.4, "significant": true}, "female": {"observed": 3.0, "expected": 3.9, "sir": null, "ci_low": null, "ci_high": null, "significant": false}, "combined": {"observed": 16.0, "expected": 18.0, "sir": null, "ci_low": null, "ci_high": null, "significant": false}}, "Pancreas": {"male": {"observed": 21.0, "expected": 18.7, "sir": 112.5, "ci_low": 69.6, "ci_high": 171.9, "significant": true}, "female": {"observed": 25.0, "expected": 20.4, "sir": 122.8, "ci_low": 79.4, "ci_high": 181.2, "significant": true}, "combined": {"observed": 46.0, "expected": 39.099999999999994, "sir": 117.64705882352943, "ci_low": null, "ci_high": null, "significant": true}}, "Hodgkin Lymphoma": {"male": {"observed": 4.0, "expected": 5.6, "sir": null, "ci_low": null, "ci_high": null, "significant": false}, "female": {"observed": 5.0, "expected": 4.8, "sir": 104.2, "ci_low": 33.6, "ci_high": 243.1, "significant": true}, "combined": {"observed": 9.0, "expected": 10.399999999999999, "sir": null, "ci_low": null, "ci_high": null, "significant": false}}, "Prostate": {"male": {"observed": 146.0, "expected": 181.6, "sir": 80.4, "ci_low": 67.9, "ci_high": 94.5, "significant": true}, "female": {"observed": 0, "expected": 0, "sir": null, "ci_low": null, "ci_high": null, "significant": false}, "combined": {"observed": 146.0, "expected": 181.6, "sir": null, "ci_low": null, "ci_high": null, "significant": false}}, "Kidney & Renal Pelvis": {"male": {"observed": 36.0, "expected": 30.1, "sir": 119.6, "ci_low": 83.7, "ci_high": 165.5, "significant": true}, "female": {"observed": 16.0, "expected": 17.8, "sir": 89.9, "ci_low": 51.4, "ci_high": 146.1, "significant": true}, "combined": {"observed": 52.0, "expected": 47.900000000000006, "sir": 108.55949895615866, "ci_low": null, "ci_high": null, "significant": true}}, "Stomach": {"male": {"observed": 18.0, "expected": 12.5, "sir": 144.2, "ci_low": 85.4, "ci_high": 227.9, "significant": true}, "female": {"observed": 9.0, "expected": 7.9, "sir": 114.2, "ci_low": 52.1, "ci_high": 216.9, "significant": true}, "combined": {"observed": 27.0, "expected": 20.4, "sir": 132.3529411764706, "ci_low": null, "ci_high": null, "significant": true}}, "Larynx": {"male": {"observed": 5.0, "expected": 8.3, "sir": 60.1, "ci_low": 19.4, "ci_high": 140.2, "significant": true}, "female": {"observed": 2.0, "expected": 2.6, "sir": null, "ci_low": null, "ci_high": null, "significant": false}, "combined": {"observed": 7.0, "expected": 10.9, "sir": null, "ci_low": null, "ci_high": null, "significant": false}}, "Testis": {"male": {"observed": 12.0, "expected": 11.3, "sir": 105.8, "ci_low": 54.6, "ci_high": 184.8, "significant": true}, "female": {"observed": 0, "expected": 0, "sir": null, "ci_low": null, "ci_high": null, "significant": false}, "combined": {"observed": 12.0, "expected": 11.3, "sir": null, "ci_low": null, "ci_high": null, "significant": false}}, "Leukemia": {"male": {"observed": 19.0, "expected": 22.2, "sir": 85.5, "ci_low": 51.4, "ci_high": 133.5, "significant": true}, "female": {"observed": 13.0, "expected": 17.3, "sir": 75.3, "ci_low": 40.1, "ci_high": 128.8, "significant": true}, "combined": {"observed": 32.0, "expected": 39.5, "sir": 81.0126582278481, "ci_low": null, "ci_high": null, "significant": true}}, "Thyroid": {"male": {"observed": 17.0, "expected": 15.2, "sir": 112.1, "ci_low": 65.3, "ci_high": 179.5, "significant": true}, "female": {"observed": 53.0, "expected": 46.6, "sir": 113.7, "ci_low": 85.1, "ci_high": 148.7, "significant": true}, "combined": {"observed": 70.0, "expected": 61.8, "sir": 113.2686084142395, "ci_low": null, "ci_high": null, "significant": true}}, "Liver and Intrahepatic Bile Ducts": {"male": {"observed": 19.0, "expected": 18.6, "sir": 102.0, "ci_low": 61.4, "ci_high": 159.3, "significant": true}, "female": {"observed": 5.0, "expected": 6.4, "sir": 77.6, "ci_low": 25.0, "ci_high": 181.2, "significant": true}, "combined": {"observed": 24.0, "expected": 25.0, "sir": 96.0, "ci_low": null, "ci_high": null, "significant": true}}, "Uteri Corpus and Uterus, NOS": {"male": {"observed": 0, "expected": 0, "sir": null, "ci_low": null, "ci_high": null, "significant": false}, "female": {"observed": 41.0, "expected": 50.5, "sir": 81.2, "ci_low": 58.3, "ci_high": 110.2, "significant": true}, "combined": {"observed": 41.0, "expected": 50.5, "sir": null, "ci_low": null, "ci_high": null, "significant": false}}, "Lung and Bronchus": {"male": {"observed": 93.0, "expected": 95.6, "sir": 97.3, "ci_low": 78.5, "ci_high": 119.2, "significant": true}, "female": {"observed": 109.0, "expected": 105.4, "sir": 103.4, "ci_low": 84.9, "ci_high": 124.7, "significant": true}, "combined": {"observed": 202.0, "expected": 201.0, "sir": 100.49751243781095, "ci_low": null, "ci_high": null, "significant": true}}, "All Sites / Types": {"male": {"observed": 667.0, "expected": 715.5, "sir": 93.2, "ci_low": 86.3, "ci_high": 100.6, "significant": true}, "female": {"observed": 750.0, "expected": 765.7, "sir": 98.0, "ci_low": 91.1, "ci_high": 105.2, "significant": true}, "combined": {"observed": 1417.0, "expected": 1481.2, "sir": 95.66567647853091, "ci_low": null, "ci_high": null, "significant": true}}}