{"08-12": {"Bladder, Urinary": {"male": {"observed": 3.0, "expected": 4.1, "sir": null, "ci_low": null, "ci_high": null, "significant": false}, "female": {"observed": 0.0, "expected": 1.4, "sir": null, "ci_low": null, "ci_high": null, "significant": false}, "combined": {"observed": 3.0, "expected": 5.5, "sir": null, "ci_low": null, "ci_high": null, "significant": false}}, "Melanoma of Skin": {"male": {"observed": 0.0, "expected": 2.8, "sir": null, "ci_low": null, "ci_high": null, "significant": false}, "female": {"observed": 1.0, "expected": 2.1, "sir": null, "ci_low": null, "ci_high": null, "significant": false}, "combined": {"observed": 1.0, "expected": 4.9, "sir": null, "ci_low": null, "ci_high": null, "significant": false}}, "Brain and Other Nervous System": {"male": {"observed": 0.0, "expected": 0.8, "sir": null, "ci_low": null, "ci_high": null, "significant": false}, "female": {"observed": 0.0, "expected": 0.6, "sir": null, "ci_low": null, "ci_high": null, "significant": false}, "combined": {"observed": 0.0, "expected": 1.4, "sir": null, "ci_low": null, "ci_high": null, "significant": false}}, "Multiple Myeloma": {"male": {"observed": 1.0, "expected": 0.8, "sir": null, "ci_low": null, "ci_high": null, "significant": false}, "female": {"observed": 0.0, "expected": 0.6, "sir": null, "ci_low": null, "ci_high": null, "significant": false}, "combined": {"observed": 1.0, "expected": 1.4, "sir": null, "ci_low": null, "ci_high": null, "significant": false}}, "Breast": {"male": {"observed": 0.0, "expected": 0.1, "sir": null, "ci_low": null, "ci_high": null, "significant": false}, "female": {"observed": 16.0, "expected": 16.6, "sir": 96.6, "ci_low": 55.2, "ci_high": 156.9, "significant": true}, "combined": {"observed": 16.0, "expected": 16.700000000000003, "sir": null, "ci_low": null, "ci_high": null, "significant": false}}, "Non-Hodgkin Lymphoma": {"male": {"observed": 5.0, "expected": 2.4, "sir": 205.6, "ci_low": 66.3, "ci_high": 479.9, "significant": true}, "female": {"observed": 4.0, "expected": 1.9, "sir": null, "ci_low": null, "ci_high": null, "significant": false}, "combined": {"observed": 9.0, "expected": 4.3, "sir": null, "ci_low": null, "ci_high": null, "significant": false}}, "Cervix Uteri": {"male": {"observed": 0, "expected": 0, "sir": null, "ci_low": null, "ci_high": null, "significant": false}, "female": {"observed": 1.0, "expected": 0.6, "sir": null, "ci_low": null, "ci_high": null, "significant": false}, "combined": {"observed": 1.0, "expected": 0.6, "sir": null, "ci_low": null, "ci_high": null, "significant": false}}, "Oral Cavity & Pharynx": {"male": {"observed": 0.0, "expected": 2.1, "sir": null, "ci_low": null, "ci_high": null, "significant": false}, "female": {"observed": 2.0, "expected": 0.8, "sir": null, "ci_low": null, "ci_high": null, "significant": false}, "combined": {"observed": 2.0, "expected": 2.9000000000000004, "sir": null, "ci_low": null, "ci_high": null, "significant": false}}, "Colon / Rectum": {"male": {"observed": 3.0, "expected": 4.7, "sir": null, "ci_low": null, "ci_high": null, "significant": false}, "female": {"observed": 1.0, "expected": 4.2, "sir": null, "ci_low": null, "ci_high": null, "significant": false}, "combined": {"observed": 4.0, "expected": 8.9, "sir": null, "ci_low": null, "ci_high": null, "significant": false}}, "Ovary": {"male": {"observed": 0, "expected": 0, "sir": null, "ci_low": null, "ci_high": null, "significant": false}, "female": {"observed": 0.0, "expected": 1.5, "sir": null, "ci_low": null, "ci_high": null, "significant": false}, "combined": {"observed": 0.0, "expected": 1.5, "sir": null, "ci_low": null, "ci_high": null, "significant": false}}, "Esophagus": {"male": {"observed": 1.0, "expected": 1.2, "sir": null, "ci_low": null, "ci_high": null, "significant": false}, "female": {"observed": 0.0, "expected": 0.3, "sir": null, "ci_low": null, "ci_high": null, "significant": false}, "combined": {"observed": 1.0, "expected": 1.5, "sir": null, "ci_low": null, "ci_high": null, "significant": false}}, "Pancreas": {"male": {"observed": 1.0, "expected": 1.4, "sir": null, "ci_low": null, "ci_high": null, "significant": false}, "female": {"observed": 0.0, "expected": 1.3, "sir": null, "ci_low": null, "ci_high": null, "significant": false}, "combined": {"observed": 1.0, "expected": 2.7, "sir": null, "ci_low": null, "ci_high": null, "significant": false}}, "Hodgkin Lymphoma": {"male": {"observed": 1.0, "expected": 0.3, "sir": null, "ci_low": null, "ci_high": null, "significant": false}, "female": {"observed": 2.0, "expected": 0.2, "sir": null, "ci_low": null, "ci_high": null, "significant": false}, "combined": {"observed": 3.0, "expected": 0.5, "sir": null, "ci_low": null, "ci_high": null, "significant": false}}, "Prostate": {"male": {"observed": 11.0, "expected": 16.4, "sir": 67.1, "ci_low": 33.4, "ci_high": 120.0, "significant": true}, "female": {"observed": 0, "expected": 0, "sir": null, "ci_low": null, "ci_high": null, "significant": false}, "combined": {"observed": 11.0, "expected": 16.4, "sir": null, "ci_low": null, "ci_high": null, "significant": false}}, "Kidney & Renal Pelvis": {"male": {"observed": 3.0, "expected": 2.4, "sir": null, "ci_low": null, "ci_high": null, "significant": false}, "female": {"observed": 0.0, "expected": 1.3, "sir": null, "ci_low": null, "ci_high": null, "significant": false}, "combined": {"observed": 3.0, "expected": 3.7, "sir": null, "ci_low": null, "ci_high": null, "significant": false}}, "Stomach": {"male": {"observed": 0.0, "expected": 1.0, "sir": null, "ci_low": null, "ci_high": null, "significant": false}, "female": {"observed": 2.0, "expected": 0.5, "sir": null, "ci_low": null, "ci_high": null, "significant": false}, "combined": {"observed": 2.0, "expected": 1.5, "sir": null, "ci_low": null, "ci_high": null, "significant": false}}, "Larynx": {"male": {"observed": 1.0, "expected": 0.7, "sir": null, "ci_low": null, "ci_high": null, "significant": false}, "female": {"observed": 0.0, "expected": 0.2, "sir": null, "ci_low": null, "ci_high": null, "significant": false}, "combined": {"observed": 1.0, "expected": 0.8999999999999999, "sir": null, "ci_low": null, "ci_high": null, "significant": false}}, "Testis": {"male": {"observed": 3.0, "expected": 0.5, "sir": null, "ci_low": null, "ci_high": null, "significant": false}, "female": {"observed": 0, "expected": 0, "sir": null, "ci_low": null, "ci_high": null, "significant": false}, "combined": {"observed": 3.0, "expected": 0.5, "sir": null, "ci_low": null, "ci_high": null, "significant": false}}, "Leukemia": {"male": {"observed": 3.0, "expected": 1.6, "sir": null, "ci_low": null, "ci_high": null, "significant": false}, "female": {"observed": 1.0, "expected": 1.1, "sir": null, "ci_low": null, "ci_high": null, "significant": false}, "combined": {"observed": 4.0, "expected": 2.7, "sir": null, "ci_low": null, "ci_high": null, "significant": false}}, "Thyroid": {"male": {"observed": 2.0, "expected": 1.1, "sir": null, "ci_low": null, "ci_high": null, "significant": false}, "female": {"observed": 4.0, "expected": 3.1, "sir": null, "ci_low": null, "ci_high": null, "significant": false}, "combined": {"observed": 6.0, "expected": 4.2, "sir": null, "ci_low": null, "ci_high": null, "significant": false}}, "Liver and Intrahepatic Bile Ducts": {"male": {"observed": 1.0, "expected": 1.5, "sir": null, "ci_low": null, "ci_high": null, "significant": false}, "female": {"observed": 0.0, "expected": 0.4, "sir": null, "ci_low": null, "ci_high": null, "significant": false}, "combined": {"observed": 1.0, "expected": 1.9, "sir": null, "ci_low": null, "ci_high": null, "significant": false}}, "Uteri Corpus and Uterus, NOS": {"male": {"observed": 0, "expected": 0, "sir": null, "ci_low": null, "ci_high": null, "significant": false}, "female": {"observed": 4.0, "expected": 3.8, "sir": null, "ci_low": null, "ci_high": null, "significant": false}, "combined": {"observed": 4.0, "expected": 3.8, "sir": null, "ci_low": null, "ci_high": null, "significant": false}}, "Lung and Bronchus": {"male": {"observed": 6.0, "expected": 7.7, "sir": 78.0, "ci_low": 28.5, "ci_high": 169.7, "significant": true}, "female": {"observed": 11.0, "expected": 7.4, "sir": 148.5, "ci_low": 74.0, "ci_high": 265.8, "significant": true}, "combined": {"observed": 17.0, "expected": 15.100000000000001, "sir": 112.58278145695364, "ci_low": null, "ci_high": null, "significant": true}}, "All Sites / Types": {"male": {"observed": 49.0, "expected": 57.9, "sir": 84.6, "ci_low": 62.6, "ci_high": 111.9, "significant": true}, "female": {"observed": 51.0, "expected": 54.1, "sir": 94.3, "ci_low": 70.2, "ci_high": 124.0, "significant": true}, "combined": {"observed": 100.0, "expected": 112.0, "sir": 89.28571428571429, "ci_low": null, "ci_high": null, "significant": true}}}, "09-13": {"Bladder, Urinary": {"male": {"observed": 4.0, "expected": 3.3, "sir": null, "ci_low": null, "ci_high": null, "significant": false}, "female": {"observed": 0.0, "expected": 1.5, "sir": null, "ci_low": null, "ci_high": null, "significant": false}, "combined": {"observed": 4.0, "expected": 4.8, "sir": null, "ci_low": null, "ci_high": null, "significant": false}}, "Melanoma of Skin": {"male": {"observed": 0.0, "expected": 2.4, "sir": null, "ci_low": null, "ci_high": null, "significant": false}, "female": {"observed": 1.0, "expected": 2.2, "sir": null, "ci_low": null, "ci_high": null, "significant": false}, "combined": {"observed": 1.0, "expected": 4.6, "sir": null, "ci_low": null, "ci_high": null, "significant": false}}, "Brain and Other Nervous System": {"male": {"observed": 0.0, "expected": 0.7, "sir": null, "ci_low": null, "ci_high": null, "significant": false}, "female": {"observed": 0.0, "expected": 0.7, "sir": null, "ci_low": null, "ci_high": null, "significant": false}, "combined": {"observed": 0.0, "expected": 1.4, "sir": null, "ci_low": null, "ci_high": null, "significant": false}}, "Multiple Myeloma": {"male": {"observed": 1.0, "expected": 0.7, "sir": null, "ci_low": null, "ci_high": null, "significant": false}, "female": {"observed": 1.0, "expected": 0.7, "sir": null, "ci_low": null, "ci_high": null, "significant": false}, "combined": {"observed": 2.0, "expected": 1.4, "sir": null, "ci_low": null, "ci_high": null, "significant": false}}, "Breast": {"male": {"observed": 0.0, "expected": 0.1, "sir": null, "ci_low": null, "ci_high": null, "significant": false}, "female": {"observed": 16.0, "expected": 18.5, "sir": 86.6, "ci_low": 49.5, "ci_high": 140.7, "significant": true}, "combined": {"observed": 16.0, "expected": 18.6, "sir": null, "ci_low": null, "ci_high": null, "significant": false}}, "Non-Hodgkin Lymphoma": {"male": {"observed": 4.0, "expected": 2.1, "sir": null, "ci_low": null, "ci_high": null, "significant": false}, "female": {"observed": 4.0, "expected": 2.2, "sir": null, "ci_low": null, "ci_high": null, "significant": false}, "combined": {"observed": 8.0, "expected": 4.300000000000001, "sir": null, "ci_low": null, "ci_high": null, "significant": false}}, "Cervix Uteri": {"male": {"observed": 0, "expected": 0, "sir": null, "ci_low": null, "ci_high": null, "significant": false}, "female": {"observed": 1.0, "expected": 0.6, "sir": null, "ci_low": null, "ci_high": null, "significant": false}, "combined": {"observed": 1.0, "expected": 0.6, "sir": null, "ci_low": null, "ci_high": null, "significant": false}}, "Oral Cavity & Pharynx": {"male": {"observed": 0.0, "expected": 2.0, "sir": null, "ci_low": null, "ci_high": null, "significant": false}, "female": {"observed": 1.0, "expected": 0.9, "sir": null, "ci_low": null, "ci_high": null, "significant": false}, "combined": {"observed": 1.0, "expected": 2.9, "sir": null, "ci_low": null, "ci_high": null, "significant": false}}, "Colon / Rectum": {"male": {"observed": 3.0, "expected": 3.9, "sir": null, "ci_low": null, "ci_high": null, "significant": false}, "female": {"observed": 1.0, "expected": 4.5, "sir": null, "ci_low": null, "ci_high": null, "significant": false}, "combined": {"observed": 4.0, "expected": 8.4, "sir": null, "ci_low": null, "ci_high": null, "significant": false}}, "Ovary": {"male": {"observed": 0, "expected": 0, "sir": null, "ci_low": null, "ci_high": null, "significant": false}, "female": {"observed": 0.0, "expected": 1.6, "sir": null, "ci_low": null, "ci_high": null, "significant": false}, "combined": {"observed": 0.0, "expected": 1.6, "sir": null, "ci_low": null, "ci_high": null, "significant": false}}, "Esophagus": {"male": {"observed": 0.0, "expected": 1.0, "sir": null, "ci_low": null, "ci_high": null, "significant": false}, "female": {"observed": 0.0, "expected": 0.3, "sir": null, "ci_low": null, "ci_high": null, "significant": false}, "combined": {"observed": 0.0, "expected": 1.3, "sir": null, "ci_low": null, "ci_high": null, "significant": false}}, "Pancreas": {"male": {"observed": 1.0, "expected": 1.3, "sir": null, "ci_low": null, "ci_high": null, "significant": false}, "female": {"observed": 0.0, "expected": 1.5, "sir": null, "ci_low": null, "ci_high": null, "significant": false}, "combined": {"observed": 1.0, "expected": 2.8, "sir": null, "ci_low": null, "ci_high": null, "significant": false}}, "Hodgkin Lymphoma": {"male": {"observed": 2.0, "expected": 0.3, "sir": null, "ci_low": null, "ci_high": null, "significant": false}, "female": {"observed": 0.0, "expected": 0.2, "sir": null, "ci_low": null, "ci_high": null, "significant": false}, "combined": {"observed": 2.0, "expected": 0.5, "sir": null, "ci_low": null, "ci_high": null, "significant": false}}, "Prostate": {"male": {"observed": 10.0, "expected": 14.1, "sir": 70.7, "ci_low": 33.9, "ci_high": 130.1, "significant": true}, "female": {"observed": 0, "expected": 0, "sir": null, "ci_low": null, "ci_high": null, "significant": false}, "combined": {"observed": 10.0, "expected": 14.1, "sir": null, "ci_low": null, "ci_high": null, "significant": false}}, "Kidney & Renal Pelvis": {"male": {"observed": 5.0, "expected": 2.2, "sir": 225.8, "ci_low": 72.8, "ci_high": 526.9, "significant": true}, "female": {"observed": 1.0, "expected": 1.4, "sir": null, "ci_low": null, "ci_high": null, "significant": false}, "combined": {"observed": 6.0, "expected": 3.6, "sir": null, "ci_low": null, "ci_high": null, "significant": false}}, "Stomach": {"male": {"observed": 0.0, "expected": 0.8, "sir": null, "ci_low": null, "ci_high": null, "significant": false}, "female": {"observed": 2.0, "expected": 0.6, "sir": null, "ci_low": null, "ci_high": null, "significant": false}, "combined": {"observed": 2.0, "expected": 1.4, "sir": null, "ci_low": null, "ci_high": null, "significant": false}}, "Larynx": {"male": {"observed": 0.0, "expected": 0.6, "sir": null, "ci_low": null, "ci_high": null, "significant": false}, "female": {"observed": 0.0, "expected": 0.2, "sir": null, "ci_low": null, "ci_high": null, "significant": false}, "combined": {"observed": 0.0, "expected": 0.8, "sir": null, "ci_low": null, "ci_high": null, "significant": false}}, "Testis": {"male": {"observed": 2.0, "expected": 0.5, "sir": null, "ci_low": null, "ci_high": null, "significant": false}, "female": {"observed": 0, "expected": 0, "sir": null, "ci_low": null, "ci_high": null, "significant": false}, "combined": {"observed": 2.0, "expected": 0.5, "sir": null, "ci_low": null, "ci_high": null, "significant": false}}, "Leukemia": {"male": {"observed": 3.0, "expected": 1.4, "sir": null, "ci_low": null, "ci_high": null, "significant": false}, "female": {"observed": 1.0, "expected": 1.2, "sir": null, "ci_low": null, "ci_high": null, "significant": false}, "combined": {"observed": 4.0, "expected": 2.5999999999999996, "sir": null, "ci_low": null, "ci_high": null, "significant": false}}, "Thyroid": {"male": {"observed": 1.0, "expected": 1.1, "sir": null, "ci_low": null, "ci_high": null, "significant": false}, "female": {"observed": 4.0, "expected": 3.2, "sir": null, "ci_low": null, "ci_high": null, "significant": false}, "combined": {"observed": 5.0, "expected": 4.300000000000001, "sir": null, "ci_low": null, "ci_high": null, "significant": false}}, "Liver and Intrahepatic Bile Ducts": {"male": {"observed": 1.0, "expected": 1.5, "sir": null, "ci_low": null, "ci_high": null, "significant": false}, "female": {"observed": 0.0, "expected": 0.5, "sir": null, "ci_low": null, "ci_high": null, "significant": false}, "combined": {"observed": 1.0, "expected": 2.0, "sir": null, "ci_low": null, "ci_high": null, "significant": false}}, "Uteri Corpus and Uterus, NOS": {"male": {"observed": 0, "expected": 0, "sir": null, "ci_low": null, "ci_high": null, "significant": false}, "female": {"observed": 2.0, "expected": 4.2, "sir": null, "ci_low": null, "ci_high": null, "significant": false}, "combined": {"observed": 2.0, "expected": 4.2, "sir": null, "ci_low": null, "ci_high": null, "significant": false}}, "Lung and Bronchus": {"male": {"observed": 8.0, "expected": 6.3, "sir": 126.5, "ci_low": 54.5, "ci_high": 249.3, "significant": true}, "female": {"observed": 9.0, "expected": 8.7, "sir": 103.5, "ci_low": 47.2, "ci_high": 196.5, "significant": true}, "combined": {"observed": 17.0, "expected": 15.0, "sir": 113.33333333333333, "ci_low": null, "ci_high": null, "significant": true}}, "All Sites / Types": {"male": {"observed": 50.0, "expected": 50.0, "sir": 100.1, "ci_low": 74.3, "ci_high": 132.0, "significant": true}, "female": {"observed": 45.0, "expected": 60.0, "sir": 75.0, "ci_low": 54.7, "ci_high": 100.4, "significant": true}, "combined": {"observed": 95.0, "expected": 110.0, "sir": 86.36363636363636, "ci_low": null, "ci_high": null, "significant": true}}}, "10-14": {"Bladder, Urinary": {"male": {"observed": 4.0, "expected": 3.7, "sir": null, "ci_low": null, "ci_high": null, "significant": false}, "female": {"observed": 0.0, "expected": 1.4, "sir": null, "ci_low": null, "ci_high": null, "significant": false}, "combined": {"observed": 4.0, "expected": 5.1, "sir": null, "ci_low": null, "ci_high": null, "significant": false}}, "Melanoma of Skin": {"male": {"observed": 0.0, "expected": 2.7, "sir": null, "ci_low": null, "ci_high": null, "significant": false}, "female": {"observed": 1.0, "expected": 2.1, "sir": null, "ci_low": null, "ci_high": null, "significant": false}, "combined": {"observed": 1.0, "expected": 4.800000000000001, "sir": null, "ci_low": null, "ci_high": null, "significant": false}}, "Brain and Other Nervous System": {"male": {"observed": 0.0, "expected": 0.8, "sir": null, "ci_low": null, "ci_high": null, "significant": false}, "female": {"observed": 0.0, "expected": 0.7, "sir": null, "ci_low": null, "ci_high": null, "significant": false}, "combined": {"observed": 0.0, "expected": 1.5, "sir": null, "ci_low": null, "ci_high": null, "significant": false}}, "Multiple Myeloma": {"male": {"observed": 1.0, "expected": 0.8, "sir": null, "ci_low": null, "ci_high": null, "significant": false}, "female": {"observed": 1.0, "expected": 0.7, "sir": null, "ci_low": null, "ci_high": null, "significant": false}, "combined": {"observed": 2.0, "expected": 1.5, "sir": null, "ci_low": null, "ci_high": null, "significant": false}}, "Breast": {"male": {"observed": 0.0, "expected": 0.1, "sir": null, "ci_low": null, "ci_high": null, "significant": false}, "female": {"observed": 18.0, "expected": 17.7, "sir": 101.7, "ci_low": 60.3, "ci_high": 160.8, "significant": true}, "combined": {"observed": 18.0, "expected": 17.8, "sir": null, "ci_low": null, "ci_high": null, "significant": false}}, "Non-Hodgkin Lymphoma": {"male": {"observed": 4.0, "expected": 2.3, "sir": null, "ci_low": null, "ci_high": null, "significant": false}, "female": {"observed": 4.0, "expected": 2.0, "sir": null, "ci_low": null, "ci_high": null, "significant": false}, "combined": {"observed": 8.0, "expected": 4.3, "sir": null, "ci_low": null, "ci_high": null, "significant": false}}, "Cervix Uteri": {"male": {"observed": 0, "expected": 0, "sir": null, "ci_low": null, "ci_high": null, "significant": false}, "female": {"observed": 1.0, "expected": 0.6, "sir": null, "ci_low": null, "ci_high": null, "significant": false}, "combined": {"observed": 1.0, "expected": 0.6, "sir": null, "ci_low": null, "ci_high": null, "significant": false}}, "Oral Cavity & Pharynx": {"male": {"observed": 0.0, "expected": 2.2, "sir": null, "ci_low": null, "ci_high": null, "significant": false}, "female": {"observed": 0.0, "expected": 0.9, "sir": null, "ci_low": null, "ci_high": null, "significant": false}, "combined": {"observed": 0.0, "expected": 3.1, "sir": null, "ci_low": null, "ci_high": null, "significant": false}}, "Colon / Rectum": {"male": {"observed": 3.0, "expected": 4.4, "sir": null, "ci_low": null, "ci_high": null, "significant": false}, "female": {"observed": 1.0, "expected": 4.1, "sir": null, "ci_low": null, "ci_high": null, "significant": false}, "combined": {"observed": 4.0, "expected": 8.5, "sir": null, "ci_low": null, "ci_high": null, "significant": false}}, "Ovary": {"male": {"observed": 0, "expected": 0, "sir": null, "ci_low": null, "ci_high": null, "significant": false}, "female": {"observed": 0.0, "expected": 1.5, "sir": null, "ci_low": null, "ci_high": null, "significant": false}, "combined": {"observed": 0.0, "expected": 1.5, "sir": null, "ci_low": null, "ci_high": null, "significant": false}}, "Esophagus": {"male": {"observed": 0.0, "expected": 1.1, "sir": null, "ci_low": null, "ci_high": null, "significant": false}, "female": {"observed": 0.0, "expected": 0.3, "sir": null, "ci_low": null, "ci_high": null, "significant": false}, "combined": {"observed": 0.0, "expected": 1.4000000000000001, "sir": null, "ci_low": null, "ci_high": null, "significant": false}}, "Pancreas": {"male": {"observed": 1.0, "expected": 1.5, "sir": null, "ci_low": null, "ci_high": null, "significant": false}, "female": {"observed": 0.0, "expected": 1.4, "sir": null, "ci_low": null, "ci_high": null, "significant": false}, "combined": {"observed": 1.0, "expected": 2.9, "sir": null, "ci_low": null, "ci_high": null, "significant": false}}, "Hodgkin Lymphoma": {"male": {"observed": 2.0, "expected": 0.3, "sir": null, "ci_low": null, "ci_high": null, "significant": false}, "female": {"observed": 0.0, "expected": 0.2, "sir": null, "ci_low": null, "ci_high": null, "significant": false}, "combined": {"observed": 2.0, "expected": 0.5, "sir": null, "ci_low": null, "ci_high": null, "significant": false}}, "Prostate": {"male": {"observed": 9.0, "expected": 14.8, "sir": 60.6, "ci_low": 27.7, "ci_high": 115.1, "significant": true}, "female": {"observed": 0, "expected": 0, "sir": null, "ci_low": null, "ci_high": null, "significant": false}, "combined": {"observed": 9.0, "expected": 14.8, "sir": null, "ci_low": null, "ci_high": null, "significant": false}}, "Kidney & Renal Pelvis": {"male": {"observed": 7.0, "expected": 2.5, "sir": 281.1, "ci_low": 112.6, "ci_high": 579.2, "significant": true}, "female": {"observed": 1.0, "expected": 1.3, "sir": null, "ci_low": null, "ci_high": null, "significant": false}, "combined": {"observed": 8.0, "expected": 3.8, "sir": null, "ci_low": null, "ci_high": null, "significant": false}}, "Stomach": {"male": {"observed": 2.0, "expected": 1.0, "sir": null, "ci_low": null, "ci_high": null, "significant": false}, "female": {"observed": 1.0, "expected": 0.5, "sir": null, "ci_low": null, "ci_high": null, "significant": false}, "combined": {"observed": 3.0, "expected": 1.5, "sir": null, "ci_low": null, "ci_high": null, "significant": false}}, "Larynx": {"male": {"observed": 0.0, "expected": 0.7, "sir": null, "ci_low": null, "ci_high": null, "significant": false}, "female": {"observed": 0.0, "expected": 0.2, "sir": null, "ci_low": null, "ci_high": null, "significant": false}, "combined": {"observed": 0.0, "expected": 0.8999999999999999, "sir": null, "ci_low": null, "ci_high": null, "significant": false}}, "Testis": {"male": {"observed": 2.0, "expected": 0.5, "sir": null, "ci_low": null, "ci_high": null, "significant": false}, "female": {"observed": 0, "expected": 0, "sir": null, "ci_low": null, "ci_high": null, "significant": false}, "combined": {"observed": 2.0, "expected": 0.5, "sir": null, "ci_low": null, "ci_high": null, "significant": false}}, "Leukemia": {"male": {"observed": 3.0, "expected": 1.6, "sir": null, "ci_low": null, "ci_high": null, "significant": false}, "female": {"observed": 1.0, "expected": 1.1, "sir": null, "ci_low": null, "ci_high": null, "significant": false}, "combined": {"observed": 4.0, "expected": 2.7, "sir": null, "ci_low": null, "ci_high": null, "significant": false}}, "Thyroid": {"male": {"observed": 1.0, "expected": 1.2, "sir": null, "ci_low": null, "ci_high": null, "significant": false}, "female": {"observed": 2.0, "expected": 3.2, "sir": null, "ci_low": null, "ci_high": null, "significant": false}, "combined": {"observed": 3.0, "expected": 4.4, "sir": null, "ci_low": null, "ci_high": null, "significant": false}}, "Liver and Intrahepatic Bile Ducts": {"male": {"observed": 1.0, "expected": 1.6, "sir": null, "ci_low": null, "ci_high": null, "significant": false}, "female": {"observed": 0.0, "expected": 0.5, "sir": null, "ci_low": null, "ci_high": null, "significant": false}, "combined": {"observed": 1.0, "expected": 2.1, "sir": null, "ci_low": null, "ci_high": null, "significant": false}}, "Uteri Corpus and Uterus, NOS": {"male": {"observed": 0, "expected": 0, "sir": null, "ci_low": null, "ci_high": null, "significant": false}, "female": {"observed": 2.0, "expected": 4.0, "sir": null, "ci_low": null, "ci_high": null, "significant": false}, "combined": {"observed": 2.0, "expected": 4.0, "sir": null, "ci_low": null, "ci_high": null, "significant": false}}, "Lung and Bronchus": {"male": {"observed": 7.0, "expected": 7.2, "sir": 97.0, "ci_low": 38.9, "ci_high": 199.9, "significant": true}, "female": {"observed": 4.0, "expected": 7.7, "sir": null, "ci_low": null, "ci_high": null, "significant": false}, "combined": {"observed": 11.0, "expected": 14.9, "sir": null, "ci_low": null, "ci_high": null, "significant": false}}, "All Sites / Types": {"male": {"observed": 51.0, "expected": 55.0, "sir": 92.7, "ci_low": 69.1, "ci_high": 121.9, "significant": true}, "female": {"observed": 38.0, "expected": 56.0, "sir": 67.8, "ci_low": 48.0, "ci_high": 93.1, "significant": true}, "combined": {"observed": 89.0, "expected": 111.0, "sir": 80.18018018018019, "ci_low": null, "ci_high": null, "significant": true}}}, "11-15": {"Bladder, Urinary": {"male": {"observed": 4.0, "expected": 4.0, "sir": null, "ci_low": null, "ci_high": null, "significant": false}, "female": {"observed": 0.0, "expected": 1.4, "sir": null, "ci_low": null, "ci_high": null, "significant": false}, "combined": {"observed": 4.0, "expected": 5.4, "sir": null, "ci_low": null, "ci_high": null, "significant": false}}, "Melanoma of Skin": {"male": {"observed": 2.0, "expected": 2.8, "sir": null, "ci_low": null, "ci_high": null, "significant": false}, "female": {"observed": 1.0, "expected": 2.1, "sir": null, "ci_low": null, "ci_high": null, "significant": false}, "combined": {"observed": 3.0, "expected": 4.9, "sir": null, "ci_low": null, "ci_high": null, "significant": false}}, "Brain and Other Nervous System": {"male": {"observed": 0.0, "expected": 0.8, "sir": null, "ci_low": null, "ci_high": null, "significant": false}, "female": {"observed": 1.0, "expected": 0.7, "sir": null, "ci_low": null, "ci_high": null, "significant": false}, "combined": {"observed": 1.0, "expected": 1.5, "sir": null, "ci_low": null, "ci_high": null, "significant": false}}, "Multiple Myeloma": {"male": {"observed": 1.0, "expected": 0.9, "sir": null, "ci_low": null, "ci_high": null, "significant": false}, "female": {"observed": 1.0, "expected": 0.7, "sir": null, "ci_low": null, "ci_high": null, "significant": false}, "combined": {"observed": 2.0, "expected": 1.6, "sir": null, "ci_low": null, "ci_high": null, "significant": false}}, "Breast": {"male": {"observed": 0.0, "expected": 0.1, "sir": null, "ci_low": null, "ci_high": null, "significant": false}, "female": {"observed": 15.0, "expected": 18.2, "sir": 82.6, "ci_low": 46.2, "ci_high": 136.2, "significant": true}, "combined": {"observed": 15.0, "expected": 18.3, "sir": null, "ci_low": null, "ci_high": null, "significant": false}}, "Non-Hodgkin Lymphoma": {"male": {"observed": 4.0, "expected": 2.4, "sir": null, "ci_low": null, "ci_high": null, "significant": false}, "female": {"observed": 5.0, "expected": 2.0, "sir": 247.1, "ci_low": 79.6, "ci_high": 576.6, "significant": true}, "combined": {"observed": 9.0, "expected": 4.4, "sir": null, "ci_low": null, "ci_high": null, "significant": false}}, "Cervix Uteri": {"male": {"observed": 0, "expected": 0, "sir": null, "ci_low": null, "ci_high": null, "significant": false}, "female": {"observed": 1.0, "expected": 0.6, "sir": null, "ci_low": null, "ci_high": null, "significant": false}, "combined": {"observed": 1.0, "expected": 0.6, "sir": null, "ci_low": null, "ci_high": null, "significant": false}}, "Oral Cavity & Pharynx": {"male": {"observed": 2.0, "expected": 2.4, "sir": null, "ci_low": null, "ci_high": null, "significant": false}, "female": {"observed": 0.0, "expected": 0.9, "sir": null, "ci_low": null, "ci_high": null, "significant": false}, "combined": {"observed": 2.0, "expected": 3.3, "sir": null, "ci_low": null, "ci_high": null, "significant": false}}, "Colon / Rectum": {"male": {"observed": 1.0, "expected": 4.5, "sir": null, "ci_low": null, "ci_high": null, "significant": false}, "female": {"observed": 2.0, "expected": 3.9, "sir": null, "ci_low": null, "ci_high": null, "significant": false}, "combined": {"observed": 3.0, "expected": 8.4, "sir": null, "ci_low": null, "ci_high": null, "significant": false}}, "Ovary": {"male": {"observed": 0, "expected": 0, "sir": null, "ci_low": null, "ci_high": null, "significant": false}, "female": {"observed": 0.0, "expected": 1.5, "sir": null, "ci_low": null, "ci_high": null, "significant": false}, "combined": {"observed": 0.0, "expected": 1.5, "sir": null, "ci_low": null, "ci_high": null, "significant": false}}, "Esophagus": {"male": {"observed": 0.0, "expected": 1.2, "sir": null, "ci_low": null, "ci_high": null, "significant": false}, "female": {"observed": 0.0, "expected": 0.3, "sir": null, "ci_low": null, "ci_high": null, "significant": false}, "combined": {"observed": 0.0, "expected": 1.5, "sir": null, "ci_low": null, "ci_high": null, "significant": false}}, "Pancreas": {"male": {"observed": 2.0, "expected": 1.6, "sir": null, "ci_low": null, "ci_high": null, "significant": false}, "female": {"observed": 0.0, "expected": 1.5, "sir": null, "ci_low": null, "ci_high": null, "significant": false}, "combined": {"observed": 2.0, "expected": 3.1, "sir": null, "ci_low": null, "ci_high": null, "significant": false}}, "Hodgkin Lymphoma": {"male": {"observed": 2.0, "expected": 0.3, "sir": null, "ci_low": null, "ci_high": null, "significant": false}, "female": {"observed": 0.0, "expected": 0.2, "sir": null, "ci_low": null, "ci_high": null, "significant": false}, "combined": {"observed": 2.0, "expected": 0.5, "sir": null, "ci_low": null, "ci_high": null, "significant": false}}, "Prostate": {"male": {"observed": 8.0, "expected": 15.0, "sir": 53.4, "ci_low": 23.0, "ci_high": 105.2, "significant": true}, "female": {"observed": 0, "expected": 0, "sir": null, "ci_low": null, "ci_high": null, "significant": false}, "combined": {"observed": 8.0, "expected": 15.0, "sir": null, "ci_low": null, "ci_high": null, "significant": false}}, "Kidney & Renal Pelvis": {"male": {"observed": 6.0, "expected": 2.7, "sir": 219.2, "ci_low": 80.0, "ci_high": 477.1, "significant": true}, "female": {"observed": 1.0, "expected": 1.4, "sir": null, "ci_low": null, "ci_high": null, "significant": false}, "combined": {"observed": 7.0, "expected": 4.1, "sir": null, "ci_low": null, "ci_high": null, "significant": false}}, "Stomach": {"male": {"observed": 2.0, "expected": 1.0, "sir": null, "ci_low": null, "ci_high": null, "significant": false}, "female": {"observed": 1.0, "expected": 0.6, "sir": null, "ci_low": null, "ci_high": null, "significant": false}, "combined": {"observed": 3.0, "expected": 1.6, "sir": null, "ci_low": null, "ci_high": null, "significant": false}}, "Larynx": {"male": {"observed": 0.0, "expected": 0.7, "sir": null, "ci_low": null, "ci_high": null, "significant": false}, "female": {"observed": 0.0, "expected": 0.2, "sir": null, "ci_low": null, "ci_high": null, "significant": false}, "combined": {"observed": 0.0, "expected": 0.8999999999999999, "sir": null, "ci_low": null, "ci_high": null, "significant": false}}, "Testis": {"male": {"observed": 2.0, "expected": 0.6, "sir": null, "ci_low": null, "ci_high": null, "significant": false}, "female": {"observed": 0, "expected": 0, "sir": null, "ci_low": null, "ci_high": null, "significant": false}, "combined": {"observed": 2.0, "expected": 0.6, "sir": null, "ci_low": null, "ci_high": null, "significant": false}}, "Leukemia": {"male": {"observed": 3.0, "expected": 1.7, "sir": null, "ci_low": null, "ci_high": null, "significant": false}, "female": {"observed": 1.0, "expected": 1.1, "sir": null, "ci_low": null, "ci_high": null, "significant": false}, "combined": {"observed": 4.0, "expected": 2.8, "sir": null, "ci_low": null, "ci_high": null, "significant": false}}, "Thyroid": {"male": {"observed": 1.0, "expected": 1.2, "sir": null, "ci_low": null, "ci_high": null, "significant": false}, "female": {"observed": 1.0, "expected": 3.2, "sir": null, "ci_low": null, "ci_high": null, "significant": false}, "combined": {"observed": 2.0, "expected": 4.4, "sir": null, "ci_low": null, "ci_high": null, "significant": false}}, "Liver and Intrahepatic Bile Ducts": {"male": {"observed": 1.0, "expected": 1.7, "sir": null, "ci_low": null, "ci_high": null, "significant": false}, "female": {"observed": 0.0, "expected": 0.5, "sir": null, "ci_low": null, "ci_high": null, "significant": false}, "combined": {"observed": 1.0, "expected": 2.2, "sir": null, "ci_low": null, "ci_high": null, "significant": false}}, "Uteri Corpus and Uterus, NOS": {"male": {"observed": 0, "expected": 0, "sir": null, "ci_low": null, "ci_high": null, "significant": false}, "female": {"observed": 3.0, "expected": 4.4, "sir": null, "ci_low": null, "ci_high": null, "significant": false}, "combined": {"observed": 3.0, "expected": 4.4, "sir": null, "ci_low": null, "ci_high": null, "significant": false}}, "Lung and Bronchus": {"male": {"observed": 6.0, "expected": 7.5, "sir": 79.8, "ci_low": 29.1, "ci_high": 173.7, "significant": true}, "female": {"observed": 5.0, "expected": 7.9, "sir": 63.0, "ci_low": 20.3, "ci_high": 147.0, "significant": true}, "combined": {"observed": 11.0, "expected": 15.4, "sir": 71.42857142857143, "ci_low": null, "ci_high": null, "significant": true}}, "All Sites / Types": {"male": {"observed": 51.0, "expected": 57.1, "sir": 89.3, "ci_low": 66.5, "ci_high": 117.4, "significant": true}, "female": {"observed": 41.0, "expected": 57.5, "sir": 71.3, "ci_low": 51.1, "ci_high": 96.7, "significant": true}, "combined": {"observed": 92.0, "expected": 114.6, "sir": 80.27923211169285, "ci_low": null, "ci_high": null, "significant": true}}}, "Average": {"Bladder, Urinary": {"male": {"observed": 3.75, "expected": 3.775, "sir": null, "significant": 0}, "female": {"observed": 0.0, "expected": 1.4249999999999998, "sir": null, "significant": 0}, "combined": {"observed": 3.75, "expected": 5.2, "sir": null, "significant": 0}}, "Melanoma of Skin": {"male": {"observed": 0.5, "expected": 2.675, "sir": null, "significant": 0}, "female": {"observed": 1.0, "expected": 2.125, "sir": null, "significant": 0}, "combined": {"observed": 1.5, "expected": 4.800000000000001, "sir": null, "significant": 0}}, "Brain and Other Nervous System": {"male": {"observed": 0.0, "expected": 0.7749999999999999, "sir": null, "significant": 0}, "female": {"observed": 0.25, "expected": 0.6749999999999999, "sir": null, "significant": 0}, "combined": {"observed": 0.25, "expected": 1.45, "sir": null, "significant": 0}}, "Multiple Myeloma": {"male": {"observed": 1.0, "expected": 0.7999999999999999, "sir": null, "significant": 0}, "female": {"observed": 0.75, "expected": 0.6749999999999999, "sir": null, "significant": 0}, "combined": {"observed": 1.75, "expected": 1.475, "sir": null, "significant": 0}}, "Breast": {"male": {"observed": 0.0, "expected": 0.1, "sir": null, "significant": 0}, "female": {"observed": 16.25, "expected": 17.75, "sir": 91.54929577464789, "significant": 1}, "combined": {"observed": 16.25, "expected": 17.85, "sir": null, "significant": 0}}, "Non-Hodgkin Lymphoma": {"male": {"observed": 4.25, "expected": 2.3, "sir": null, "significant": 0}, "female": {"observed": 4.25, "expected": 2.025, "sir": null, "significant": 0}, "combined": {"observed": 8.5, "expected": 4.325000000000001, "sir": null, "significant": 0}}, "Cervix Uteri": {"male": {"observed": 0.0, "expected": 0.0, "sir": null, "significant": 0}, "female": {"observed": 1.0, "expected": 0.6, "sir": null, "significant": 0}, "combined": {"observed": 1.0, "expected": 0.6, "sir": null, "significant": 0}}, "Oral Cavity & Pharynx": {"male": {"observed": 0.5, "expected": 2.175, "sir": null, "significant": 0}, "female": {"observed": 0.75, "expected": 0.875, "sir": null, "significant": 0}, "combined": {"observed": 1.25, "expected": 3.05, "sir": null, "significant": 0}}, "Colon / Rectum": {"male": {"observed": 2.5, "expected": 4.375, "sir": null, "significant": 0}, "female": {"observed": 1.25, "expected": 4.175, "sir": null, "significant": 0}, "combined": {"observed": 3.75, "expected": 8.55, "sir": null, "significant": 0}}, "Ovary": {"male": {"observed": 0.0, "expected": 0.0, "sir": null, "significant": 0}, "female": {"observed": 0.0, "expected": 1.525, "sir": null, "significant": 0}, "combined": {"observed": 0.0, "expected": 1.525, "sir": null, "significant": 0}}, "Esophagus": {"male": {"observed": 0.25, "expected": 1.125, "sir": null, "significant": 0}, "female": {"observed": 0.0, "expected": 0.3, "sir": null, "significant": 0}, "combined": {"observed": 0.25, "expected": 1.425, "sir": null, "significant": 0}}, "Pancreas": {"male": {"observed": 1.25, "expected": 1.4500000000000002, "sir": null, "significant": 0}, "female": {"observed": 0.0, "expected": 1.4249999999999998, "sir": null, "significant": 0}, "combined": {"observed": 1.25, "expected": 2.875, "sir": null, "significant": 0}}, "Hodgkin Lymphoma": {"male": {"observed": 1.75, "expected": 0.3, "sir": null, "significant": 0}, "female": {"observed": 0.5, "expected": 0.2, "sir": null, "significant": 0}, "combined": {"observed": 2.25, "expected": 0.5, "sir": null, "significant": 0}}, "Prostate": {"male": {"observed": 9.5, "expected": 15.075, "sir": 63.018242122719734, "significant": 1}, "female": {"observed": 0.0, "expected": 0.0, "sir": null, "significant": 0}, "combined": {"observed": 9.5, "expected": 15.075, "sir": null, "significant": 0}}, "Kidney & Renal Pelvis": {"male": {"observed": 5.25, "expected": 2.45, "sir": null, "significant": 0}, "female": {"observed": 0.75, "expected": 1.35, "sir": null, "significant": 0}, "combined": {"observed": 6.0, "expected": 3.8000000000000003, "sir": null, "significant": 0}}, "Stomach": {"male": {"observed": 1.0, "expected": 0.95, "sir": null, "significant": 0}, "female": {"observed": 1.5, "expected": 0.55, "sir": null, "significant": 0}, "combined": {"observed": 2.5, "expected": 1.5, "sir": null, "significant": 0}}, "Larynx": {"male": {"observed": 0.25, "expected": 0.6749999999999999, "sir": null, "significant": 0}, "female": {"observed": 0.0, "expected": 0.2, "sir": null, "significant": 0}, "combined": {"observed": 0.25, "expected": 0.8749999999999999, "sir": null, "significant": 0}}, "Testis": {"male": {"observed": 2.25, "expected": 0.525, "sir": null, "significant": 0}, "female": {"observed": 0.0, "expected": 0.0, "sir": null, "significant": 0}, "combined": {"observed": 2.25, "expected": 0.525, "sir": null, "significant": 0}}, "Leukemia": {"male": {"observed": 3.0, "expected": 1.575, "sir": null, "significant": 0}, "female": {"observed": 1.0, "expected": 1.125, "sir": null, "significant": 0}, "combined": {"observed": 4.0, "expected": 2.7, "sir": null, "significant": 0}}, "Thyroid": {"male": {"observed": 1.25, "expected": 1.1500000000000001, "sir": null, "significant": 0}, "female": {"observed": 2.75, "expected": 3.175, "sir": null, "significant": 0}, "combined": {"observed": 4.0, "expected": 4.325, "sir": null, "significant": 0}}, "Liver and Intrahepatic Bile Ducts": {"male": {"observed": 1.0, "expected": 1.575, "sir": null, "significant": 0}, "female": {"observed": 0.0, "expected": 0.475, "sir": null, "significant": 0}, "combined": {"observed": 1.0, "expected": 2.05, "sir": null, "significant": 0}}, "Uteri Corpus and Uterus, NOS": {"male": {"observed": 0.0, "expected": 0.0, "sir": null, "significant": 0}, "female": {"observed": 2.75, "expected": 4.1, "sir": null, "significant": 0}, "combined": {"observed": 2.75, "expected": 4.1, "sir": null, "significant": 0}}, "Lung and Bronchus": {"male": {"observed": 6.75, "expected": 7.175, "sir": 94.07665505226481, "significant": 1}, "female": {"observed": 7.25, "expected": 7.925000000000001, "sir": null, "significant": 0}, "combined": {"observed": 14.0, "expected": 15.1, "sir": null, "significant": 0}}, "All Sites / Types": {"male": {"observed": 50.25, "expected": 55.0, "sir": 91.36363636363637, "significant": 1}, "female": {"observed": 43.75, "expected": 56.9, "sir": 76.88927943760984, "significant": 1}, "combined": {"observed": 94.0, "expected": 111.9, "sir": 84.0035746201966, "significant": 1}}}, "Rank": {"08-12": {"All Sites / Types": {"male": 71, "female": 130, "combined": 81}}, "09-13": {"All Sites / Types": {"male": 214, "female": 39, "combined": 73}}, "10-14": {"All Sites / Types": {"male": 148, "female": 26, "combined": 46}}, "11-15": {"All Sites / Types": {"male": 125, "female": 31, "combined": 50}}, "Average": {"All Sites / Types": {"male": 132, "female": 38, "combined": 59}}}}