{"08-12": {"Bladder, Urinary": {"male": {"observed": 60.0, "expected": 55.2, "sir": 108.7, "ci_low": 82.9, "ci_high": 139.9, "significant": true}, "female": {"observed": 25.0, "expected": 22.2, "sir": 112.4, "ci_low": 72.7, "ci_high": 165.9, "significant": true}, "combined": {"observed": 85.0, "expected": 77.4, "sir": 109.81912144702841, "ci_low": null, "ci_high": null, "significant": true}}, "Melanoma of Skin": {"male": {"observed": 36.0, "expected": 37.4, "sir": 96.3, "ci_low": 67.5, "ci_high": 133.4, "significant": true}, "female": {"observed": 27.0, "expected": 33.3, "sir": 81.0, "ci_low": 53.4, "ci_high": 117.8, "significant": true}, "combined": {"observed": 63.0, "expected": 70.69999999999999, "sir": 89.10891089108912, "ci_low": null, "ci_high": null, "significant": true}}, "Brain and Other Nervous System": {"male": {"observed": 14.0, "expected": 11.4, "sir": 122.3, "ci_low": 66.8, "ci_high": 205.2, "significant": true}, "female": {"observed": 10.0, "expected": 10.3, "sir": 97.3, "ci_low": 46.6, "ci_high": 179.0, "significant": true}, "combined": {"observed": 24.0, "expected": 21.700000000000003, "sir": 110.59907834101381, "ci_low": null, "ci_high": null, "significant": true}}, "Multiple Myeloma": {"male": {"observed": 8.0, "expected": 10.7, "sir": 74.5, "ci_low": 32.1, "ci_high": 146.9, "significant": true}, "female": {"observed": 8.0, "expected": 9.5, "sir": 84.3, "ci_low": 36.3, "ci_high": 166.2, "significant": true}, "combined": {"observed": 16.0, "expected": 20.2, "sir": 79.20792079207921, "ci_low": null, "ci_high": null, "significant": true}}, "Breast": {"male": {"observed": 1.0, "expected": 1.8, "sir": null, "ci_low": null, "ci_high": null, "significant": false}, "female": {"observed": 253.0, "expected": 247.4, "sir": 102.2, "ci_low": 90.0, "ci_high": 115.7, "significant": true}, "combined": {"observed": 254.0, "expected": 249.20000000000002, "sir": null, "ci_low": null, "ci_high": null, "significant": false}}, "Non-Hodgkin Lymphoma": {"male": {"observed": 40.0, "expected": 33.2, "sir": 120.6, "ci_low": 86.1, "ci_high": 164.2, "significant": true}, "female": {"observed": 45.0, "expected": 30.2, "sir": 149.2, "ci_low": 108.8, "ci_high": 199.6, "significant": true}, "combined": {"observed": 85.0, "expected": 63.400000000000006, "sir": 134.06940063091483, "ci_low": null, "ci_high": null, "significant": true}}, "Cervix Uteri": {"male": {"observed": 0, "expected": 0, "sir": null, "ci_low": null, "ci_high": null, "significant": false}, "female": {"observed": 6.0, "expected": 9.2, "sir": 65.4, "ci_low": 23.9, "ci_high": 142.4, "significant": true}, "combined": {"observed": 6.0, "expected": 9.2, "sir": null, "ci_low": null, "ci_high": null, "significant": false}}, "Oral Cavity & Pharynx": {"male": {"observed": 38.0, "expected": 27.0, "sir": 141.0, "ci_low": 99.8, "ci_high": 193.5, "significant": true}, "female": {"observed": 18.0, "expected": 12.6, "sir": 143.0, "ci_low": 84.7, "ci_high": 226.0, "significant": true}, "combined": {"observed": 56.0, "expected": 39.6, "sir": 141.41414141414143, "ci_low": null, "ci_high": null, "significant": true}}, "Colon / Rectum": {"male": {"observed": 81.0, "expected": 63.2, "sir": 128.2, "ci_low": 101.8, "ci_high": 159.4, "significant": true}, "female": {"observed": 74.0, "expected": 69.2, "sir": 106.9, "ci_low": 84.0, "ci_high": 134.2, "significant": true}, "combined": {"observed": 155.0, "expected": 132.4, "sir": 117.06948640483384, "ci_low": null, "ci_high": null, "significant": true}}, "Ovary": {"male": {"observed": 0, "expected": 0, "sir": null, "ci_low": null, "ci_high": null, "significant": false}, "female": {"observed": 23.0, "expected": 22.6, "sir": 101.7, "ci_low": 64.4, "ci_high": 152.6, "significant": true}, "combined": {"observed": 23.0, "expected": 22.6, "sir": null, "ci_low": null, "ci_high": null, "significant": false}}, "Esophagus": {"male": {"observed": 14.0, "expected": 15.0, "sir": 93.1, "ci_low": 50.8, "ci_high": 156.2, "significant": true}, "female": {"observed": 4.0, "expected": 4.2, "sir": null, "ci_low": null, "ci_high": null, "significant": false}, "combined": {"observed": 18.0, "expected": 19.2, "sir": null, "ci_low": null, "ci_high": null, "significant": false}}, "Pancreas": {"male": {"observed": 25.0, "expected": 19.0, "sir": 131.3, "ci_low": 85.0, "ci_high": 193.9, "significant": true}, "female": {"observed": 30.0, "expected": 21.8, "sir": 137.6, "ci_low": 92.8, "ci_high": 196.4, "significant": true}, "combined": {"observed": 55.0, "expected": 40.8, "sir": 134.80392156862746, "ci_low": null, "ci_high": null, "significant": true}}, "Hodgkin Lymphoma": {"male": {"observed": 7.0, "expected": 5.1, "sir": 136.0, "ci_low": 54.5, "ci_high": 280.3, "significant": true}, "female": {"observed": 4.0, "expected": 4.4, "sir": null, "ci_low": null, "ci_high": null, "significant": false}, "combined": {"observed": 11.0, "expected": 9.5, "sir": null, "ci_low": null, "ci_high": null, "significant": false}}, "Prostate": {"male": {"observed": 175.0, "expected": 201.1, "sir": 87.0, "ci_low": 74.6, "ci_high": 100.9, "significant": true}, "female": {"observed": 0, "expected": 0, "sir": null, "ci_low": null, "ci_high": null, "significant": false}, "combined": {"observed": 175.0, "expected": 201.1, "sir": null, "ci_low": null, "ci_high": null, "significant": false}}, "Kidney & Renal Pelvis": {"male": {"observed": 37.0, "expected": 31.6, "sir": 117.2, "ci_low": 82.5, "ci_high": 161.6, "significant": true}, "female": {"observed": 23.0, "expected": 19.5, "sir": 118.0, "ci_low": 74.8, "ci_high": 177.1, "significant": true}, "combined": {"observed": 60.0, "expected": 51.1, "sir": 117.41682974559686, "ci_low": null, "ci_high": null, "significant": true}}, "Stomach": {"male": {"observed": 21.0, "expected": 13.2, "sir": 159.1, "ci_low": 98.5, "ci_high": 243.3, "significant": true}, "female": {"observed": 8.0, "expected": 8.7, "sir": 91.7, "ci_low": 39.5, "ci_high": 180.6, "significant": true}, "combined": {"observed": 29.0, "expected": 21.9, "sir": 132.4200913242009, "ci_low": null, "ci_high": null, "significant": true}}, "Larynx": {"male": {"observed": 9.0, "expected": 8.4, "sir": 107.6, "ci_low": 49.1, "ci_high": 204.3, "significant": true}, "female": {"observed": 4.0, "expected": 2.9, "sir": null, "ci_low": null, "ci_high": null, "significant": false}, "combined": {"observed": 13.0, "expected": 11.3, "sir": null, "ci_low": null, "ci_high": null, "significant": false}}, "Testis": {"male": {"observed": 9.0, "expected": 9.1, "sir": 98.4, "ci_low": 44.9, "ci_high": 186.9, "significant": true}, "female": {"observed": 0, "expected": 0, "sir": null, "ci_low": null, "ci_high": null, "significant": false}, "combined": {"observed": 9.0, "expected": 9.1, "sir": null, "ci_low": null, "ci_high": null, "significant": false}}, "Leukemia": {"male": {"observed": 20.0, "expected": 23.1, "sir": 86.5, "ci_low": 52.8, "ci_high": 133.6, "significant": true}, "female": {"observed": 19.0, "expected": 18.5, "sir": 102.6, "ci_low": 61.7, "ci_high": 160.2, "significant": true}, "combined": {"observed": 39.0, "expected": 41.6, "sir": 93.75, "ci_low": null, "ci_high": null, "significant": true}}, "Thyroid": {"male": {"observed": 15.0, "expected": 15.4, "sir": 97.3, "ci_low": 54.4, "ci_high": 160.5, "significant": true}, "female": {"observed": 48.0, "expected": 49.4, "sir": 97.1, "ci_low": 71.6, "ci_high": 128.7, "significant": true}, "combined": {"observed": 63.0, "expected": 64.8, "sir": 97.22222222222221, "ci_low": null, "ci_high": null, "significant": true}}, "Liver and Intrahepatic Bile Ducts": {"male": {"observed": 18.0, "expected": 19.6, "sir": 91.9, "ci_low": 54.5, "ci_high": 145.3, "significant": true}, "female": {"observed": 4.0, "expected": 6.7, "sir": null, "ci_low": null, "ci_high": null, "significant": false}, "combined": {"observed": 22.0, "expected": 26.3, "sir": null, "ci_low": null, "ci_high": null, "significant": false}}, "Uteri Corpus and Uterus, NOS": {"male": {"observed": 0, "expected": 0, "sir": null, "ci_low": null, "ci_high": null, "significant": false}, "female": {"observed": 61.0, "expected": 55.5, "sir": 109.9, "ci_low": 84.1, "ci_high": 141.2, "significant": true}, "combined": {"observed": 61.0, "expected": 55.5, "sir": null, "ci_low": null, "ci_high": null, "significant": false}}, "Lung and Bronchus": {"male": {"observed": 106.0, "expected": 99.7, "sir": 106.3, "ci_low": 87.0, "ci_high": 128.6, "significant": true}, "female": {"observed": 145.0, "expected": 113.2, "sir": 128.1, "ci_low": 108.1, "ci_high": 150.7, "significant": true}, "combined": {"observed": 251.0, "expected": 212.9, "sir": 117.89572569281353, "ci_low": null, "ci_high": null, "significant": true}}, "All Sites / Types": {"male": {"observed": 785.0, "expected": 758.4, "sir": 103.5, "ci_low": 96.4, "ci_high": 111.0, "significant": true}, "female": {"observed": 908.0, "expected": 838.5, "sir": 108.3, "ci_low": 101.4, "ci_high": 115.6, "significant": true}, "combined": {"observed": 1693.0, "expected": 1596.9, "sir": 106.01790970004383, "ci_low": null, "ci_high": null, "significant": true}}}, "09-13": {"Bladder, Urinary": {"male": {"observed": 57.0, "expected": 59.1, "sir": 96.4, "ci_low": 73.0, "ci_high": 124.9, "significant": true}, "female": {"observed": 27.0, "expected": 21.7, "sir": 124.5, "ci_low": 82.0, "ci_high": 181.1, "significant": true}, "combined": {"observed": 84.0, "expected": 80.8, "sir": 103.96039603960396, "ci_low": null, "ci_high": null, "significant": true}}, "Melanoma of Skin": {"male": {"observed": 24.0, "expected": 38.7, "sir": 62.0, "ci_low": 39.7, "ci_high": 92.3, "significant": true}, "female": {"observed": 20.0, "expected": 32.3, "sir": 61.9, "ci_low": 37.8, "ci_high": 95.6, "significant": true}, "combined": {"observed": 44.0, "expected": 71.0, "sir": 61.97183098591549, "ci_low": null, "ci_high": null, "significant": true}}, "Brain and Other Nervous System": {"male": {"observed": 14.0, "expected": 12.1, "sir": 115.8, "ci_low": 63.3, "ci_high": 194.4, "significant": true}, "female": {"observed": 11.0, "expected": 10.1, "sir": 109.0, "ci_low": 54.3, "ci_high": 195.0, "significant": true}, "combined": {"observed": 25.0, "expected": 22.2, "sir": 112.61261261261262, "ci_low": null, "ci_high": null, "significant": true}}, "Multiple Myeloma": {"male": {"observed": 10.0, "expected": 11.9, "sir": 84.0, "ci_low": 40.2, "ci_high": 154.6, "significant": true}, "female": {"observed": 8.0, "expected": 9.8, "sir": 81.4, "ci_low": 35.1, "ci_high": 160.5, "significant": true}, "combined": {"observed": 18.0, "expected": 21.700000000000003, "sir": 82.94930875576036, "ci_low": null, "ci_high": null, "significant": true}}, "Breast": {"male": {"observed": 2.0, "expected": 2.0, "sir": null, "ci_low": null, "ci_high": null, "significant": false}, "female": {"observed": 255.0, "expected": 244.4, "sir": 104.3, "ci_low": 91.9, "ci_high": 117.9, "significant": true}, "combined": {"observed": 257.0, "expected": 246.4, "sir": null, "ci_low": null, "ci_high": null, "significant": false}}, "Non-Hodgkin Lymphoma": {"male": {"observed": 40.0, "expected": 34.9, "sir": 114.8, "ci_low": 82.0, "ci_high": 156.3, "significant": true}, "female": {"observed": 41.0, "expected": 30.7, "sir": 133.5, "ci_low": 95.8, "ci_high": 181.1, "significant": true}, "combined": {"observed": 81.0, "expected": 65.6, "sir": 123.47560975609757, "ci_low": null, "ci_high": null, "significant": true}}, "Cervix Uteri": {"male": {"observed": 0, "expected": 0, "sir": null, "ci_low": null, "ci_high": null, "significant": false}, "female": {"observed": 4.0, "expected": 8.8, "sir": null, "ci_low": null, "ci_high": null, "significant": false}, "combined": {"observed": 4.0, "expected": 8.8, "sir": null, "ci_low": null, "ci_high": null, "significant": false}}, "Oral Cavity & Pharynx": {"male": {"observed": 39.0, "expected": 28.0, "sir": 139.0, "ci_low": 98.9, "ci_high": 190.1, "significant": true}, "female": {"observed": 16.0, "expected": 12.9, "sir": 123.7, "ci_low": 70.6, "ci_high": 200.8, "significant": true}, "combined": {"observed": 55.0, "expected": 40.9, "sir": 134.47432762836186, "ci_low": null, "ci_high": null, "significant": true}}, "Colon / Rectum": {"male": {"observed": 77.0, "expected": 65.7, "sir": 117.3, "ci_low": 92.5, "ci_high": 146.6, "significant": true}, "female": {"observed": 67.0, "expected": 67.7, "sir": 99.0, "ci_low": 76.7, "ci_high": 125.8, "significant": true}, "combined": {"observed": 144.0, "expected": 133.4, "sir": 107.94602698650675, "ci_low": null, "ci_high": null, "significant": true}}, "Ovary": {"male": {"observed": 0, "expected": 0, "sir": null, "ci_low": null, "ci_high": null, "significant": false}, "female": {"observed": 20.0, "expected": 21.9, "sir": 91.3, "ci_low": 55.8, "ci_high": 141.1, "significant": true}, "combined": {"observed": 20.0, "expected": 21.9, "sir": null, "ci_low": null, "ci_high": null, "significant": false}}, "Esophagus": {"male": {"observed": 12.0, "expected": 15.5, "sir": 77.2, "ci_low": 39.9, "ci_high": 134.9, "significant": true}, "female": {"observed": 4.0, "expected": 4.2, "sir": null, "ci_low": null, "ci_high": null, "significant": false}, "combined": {"observed": 16.0, "expected": 19.7, "sir": null, "ci_low": null, "ci_high": null, "significant": false}}, "Pancreas": {"male": {"observed": 25.0, "expected": 20.9, "sir": 119.7, "ci_low": 77.5, "ci_high": 176.8, "significant": true}, "female": {"observed": 28.0, "expected": 22.0, "sir": 127.0, "ci_low": 84.4, "ci_high": 183.6, "significant": true}, "combined": {"observed": 53.0, "expected": 42.9, "sir": 123.54312354312356, "ci_low": null, "ci_high": null, "significant": true}}, "Hodgkin Lymphoma": {"male": {"observed": 6.0, "expected": 5.0, "sir": 119.5, "ci_low": 43.6, "ci_high": 260.0, "significant": true}, "female": {"observed": 3.0, "expected": 4.0, "sir": null, "ci_low": null, "ci_high": null, "significant": false}, "combined": {"observed": 9.0, "expected": 9.0, "sir": null, "ci_low": null, "ci_high": null, "significant": false}}, "Prostate": {"male": {"observed": 165.0, "expected": 194.1, "sir": 85.0, "ci_low": 72.5, "ci_high": 99.0, "significant": true}, "female": {"observed": 0, "expected": 0, "sir": null, "ci_low": null, "ci_high": null, "significant": false}, "combined": {"observed": 165.0, "expected": 194.1, "sir": null, "ci_low": null, "ci_high": null, "significant": false}}, "Kidney & Renal Pelvis": {"male": {"observed": 32.0, "expected": 32.8, "sir": 97.6, "ci_low": 66.8, "ci_high": 137.8, "significant": true}, "female": {"observed": 24.0, "expected": 19.2, "sir": 124.8, "ci_low": 79.9, "ci_high": 185.7, "significant": true}, "combined": {"observed": 56.0, "expected": 52.0, "sir": 107.6923076923077, "ci_low": null, "ci_high": null, "significant": true}}, "Stomach": {"male": {"observed": 20.0, "expected": 14.0, "sir": 142.6, "ci_low": 87.1, "ci_high": 220.2, "significant": true}, "female": {"observed": 6.0, "expected": 8.7, "sir": 68.8, "ci_low": 25.1, "ci_high": 149.7, "significant": true}, "combined": {"observed": 26.0, "expected": 22.7, "sir": 114.53744493392071, "ci_low": null, "ci_high": null, "significant": true}}, "Larynx": {"male": {"observed": 9.0, "expected": 9.0, "sir": 100.4, "ci_low": 45.8, "ci_high": 190.6, "significant": true}, "female": {"observed": 4.0, "expected": 2.8, "sir": null, "ci_low": null, "ci_high": null, "significant": false}, "combined": {"observed": 13.0, "expected": 11.8, "sir": null, "ci_low": null, "ci_high": null, "significant": false}}, "Testis": {"male": {"observed": 7.0, "expected": 9.7, "sir": 72.5, "ci_low": 29.1, "ci_high": 149.4, "significant": true}, "female": {"observed": 0, "expected": 0, "sir": null, "ci_low": null, "ci_high": null, "significant": false}, "combined": {"observed": 7.0, "expected": 9.7, "sir": null, "ci_low": null, "ci_high": null, "significant": false}}, "Leukemia": {"male": {"observed": 22.0, "expected": 24.6, "sir": 89.5, "ci_low": 56.1, "ci_high": 135.5, "significant": true}, "female": {"observed": 19.0, "expected": 18.6, "sir": 102.0, "ci_low": 61.4, "ci_high": 159.4, "significant": true}, "combined": {"observed": 41.0, "expected": 43.2, "sir": 94.90740740740739, "ci_low": null, "ci_high": null, "significant": true}}, "Thyroid": {"male": {"observed": 16.0, "expected": 15.7, "sir": 101.8, "ci_low": 58.2, "ci_high": 165.4, "significant": true}, "female": {"observed": 56.0, "expected": 48.3, "sir": 115.9, "ci_low": 87.6, "ci_high": 150.6, "significant": true}, "combined": {"observed": 72.0, "expected": 64.0, "sir": 112.5, "ci_low": null, "ci_high": null, "significant": true}}, "Liver and Intrahepatic Bile Ducts": {"male": {"observed": 18.0, "expected": 20.6, "sir": 87.2, "ci_low": 51.7, "ci_high": 137.9, "significant": true}, "female": {"observed": 4.0, "expected": 6.9, "sir": null, "ci_low": null, "ci_high": null, "significant": false}, "combined": {"observed": 22.0, "expected": 27.5, "sir": null, "ci_low": null, "ci_high": null, "significant": false}}, "Uteri Corpus and Uterus, NOS": {"male": {"observed": 0, "expected": 0, "sir": null, "ci_low": null, "ci_high": null, "significant": false}, "female": {"observed": 58.0, "expected": 54.8, "sir": 105.8, "ci_low": 80.3, "ci_high": 136.8, "significant": true}, "combined": {"observed": 58.0, "expected": 54.8, "sir": null, "ci_low": null, "ci_high": null, "significant": false}}, "Lung and Bronchus": {"male": {"observed": 105.0, "expected": 103.3, "sir": 101.7, "ci_low": 83.1, "ci_high": 123.1, "significant": true}, "female": {"observed": 152.0, "expected": 110.2, "sir": 138.0, "ci_low": 116.9, "ci_high": 161.8, "significant": true}, "combined": {"observed": 257.0, "expected": 213.5, "sir": 120.37470725995317, "ci_low": null, "ci_high": null, "significant": true}}, "All Sites / Types": {"male": {"observed": 749.0, "expected": 780.4, "sir": 96.0, "ci_low": 89.2, "ci_high": 103.1, "significant": true}, "female": {"observed": 896.0, "expected": 827.6, "sir": 108.3, "ci_low": 101.3, "ci_high": 115.6, "significant": true}, "combined": {"observed": 1645.0, "expected": 1608.0, "sir": 102.30099502487562, "ci_low": null, "ci_high": null, "significant": true}}}, "10-14": {"Bladder, Urinary": {"male": {"observed": 53.0, "expected": 60.1, "sir": 88.3, "ci_low": 66.1, "ci_high": 115.4, "significant": true}, "female": {"observed": 31.0, "expected": 21.8, "sir": 142.2, "ci_low": 96.6, "ci_high": 201.9, "significant": true}, "combined": {"observed": 84.0, "expected": 81.9, "sir": 102.56410256410255, "ci_low": null, "ci_high": null, "significant": true}}, "Melanoma of Skin": {"male": {"observed": 28.0, "expected": 38.7, "sir": 72.3, "ci_low": 48.1, "ci_high": 104.6, "significant": true}, "female": {"observed": 19.0, "expected": 31.9, "sir": 59.6, "ci_low": 35.9, "ci_high": 93.1, "significant": true}, "combined": {"observed": 47.0, "expected": 70.6, "sir": 66.57223796033995, "ci_low": null, "ci_high": null, "significant": true}}, "Brain and Other Nervous System": {"male": {"observed": 14.0, "expected": 12.2, "sir": 115.2, "ci_low": 62.9, "ci_high": 193.3, "significant": true}, "female": {"observed": 12.0, "expected": 10.3, "sir": 116.3, "ci_low": 60.0, "ci_high": 203.2, "significant": true}, "combined": {"observed": 26.0, "expected": 22.5, "sir": 115.55555555555554, "ci_low": null, "ci_high": null, "significant": true}}, "Multiple Myeloma": {"male": {"observed": 11.0, "expected": 12.3, "sir": 89.6, "ci_low": 44.7, "ci_high": 160.4, "significant": true}, "female": {"observed": 7.0, "expected": 10.1, "sir": 69.6, "ci_low": 27.9, "ci_high": 143.4, "significant": true}, "combined": {"observed": 18.0, "expected": 22.4, "sir": 80.35714285714286, "ci_low": null, "ci_high": null, "significant": true}}, "Breast": {"male": {"observed": 2.0, "expected": 2.1, "sir": null, "ci_low": null, "ci_high": null, "significant": false}, "female": {"observed": 246.0, "expected": 250.4, "sir": 98.2, "ci_low": 86.4, "ci_high": 111.3, "significant": true}, "combined": {"observed": 248.0, "expected": 252.5, "sir": null, "ci_low": null, "ci_high": null, "significant": false}}, "Non-Hodgkin Lymphoma": {"male": {"observed": 33.0, "expected": 35.0, "sir": 94.4, "ci_low": 65.0, "ci_high": 132.6, "significant": true}, "female": {"observed": 41.0, "expected": 31.2, "sir": 131.4, "ci_low": 94.3, "ci_high": 178.2, "significant": true}, "combined": {"observed": 74.0, "expected": 66.2, "sir": 111.78247734138974, "ci_low": null, "ci_high": null, "significant": true}}, "Cervix Uteri": {"male": {"observed": 0, "expected": 0, "sir": null, "ci_low": null, "ci_high": null, "significant": false}, "female": {"observed": 8.0, "expected": 8.9, "sir": 90.2, "ci_low": 38.9, "ci_high": 177.8, "significant": true}, "combined": {"observed": 8.0, "expected": 8.9, "sir": null, "ci_low": null, "ci_high": null, "significant": false}}, "Oral Cavity & Pharynx": {"male": {"observed": 32.0, "expected": 28.9, "sir": 110.9, "ci_low": 75.8, "ci_high": 156.5, "significant": true}, "female": {"observed": 14.0, "expected": 13.3, "sir": 105.2, "ci_low": 57.5, "ci_high": 176.6, "significant": true}, "combined": {"observed": 46.0, "expected": 42.2, "sir": 109.00473933649289, "ci_low": null, "ci_high": null, "significant": true}}, "Colon / Rectum": {"male": {"observed": 68.0, "expected": 66.2, "sir": 102.7, "ci_low": 79.8, "ci_high": 130.2, "significant": true}, "female": {"observed": 72.0, "expected": 65.8, "sir": 109.4, "ci_low": 85.6, "ci_high": 137.7, "significant": true}, "combined": {"observed": 140.0, "expected": 132.0, "sir": 106.06060606060606, "ci_low": null, "ci_high": null, "significant": true}}, "Ovary": {"male": {"observed": 0, "expected": 0, "sir": null, "ci_low": null, "ci_high": null, "significant": false}, "female": {"observed": 20.0, "expected": 21.7, "sir": 92.3, "ci_low": 56.4, "ci_high": 142.6, "significant": true}, "combined": {"observed": 20.0, "expected": 21.7, "sir": null, "ci_low": null, "ci_high": null, "significant": false}}, "Esophagus": {"male": {"observed": 11.0, "expected": 15.3, "sir": 71.7, "ci_low": 35.8, "ci_high": 128.4, "significant": true}, "female": {"observed": 5.0, "expected": 4.3, "sir": 117.2, "ci_low": 37.8, "ci_high": 273.5, "significant": true}, "combined": {"observed": 16.0, "expected": 19.6, "sir": 81.63265306122447, "ci_low": null, "ci_high": null, "significant": true}}, "Pancreas": {"male": {"observed": 27.0, "expected": 21.5, "sir": 125.6, "ci_low": 82.7, "ci_high": 182.7, "significant": true}, "female": {"observed": 24.0, "expected": 22.5, "sir": 106.5, "ci_low": 68.2, "ci_high": 158.5, "significant": true}, "combined": {"observed": 51.0, "expected": 44.0, "sir": 115.90909090909092, "ci_low": null, "ci_high": null, "significant": true}}, "Hodgkin Lymphoma": {"male": {"observed": 6.0, "expected": 5.0, "sir": 118.9, "ci_low": 43.4, "ci_high": 258.8, "significant": true}, "female": {"observed": 3.0, "expected": 4.1, "sir": null, "ci_low": null, "ci_high": null, "significant": false}, "combined": {"observed": 9.0, "expected": 9.1, "sir": null, "ci_low": null, "ci_high": null, "significant": false}}, "Prostate": {"male": {"observed": 148.0, "expected": 184.5, "sir": 80.2, "ci_low": 67.8, "ci_high": 94.2, "significant": true}, "female": {"observed": 0, "expected": 0, "sir": null, "ci_low": null, "ci_high": null, "significant": false}, "combined": {"observed": 148.0, "expected": 184.5, "sir": null, "ci_low": null, "ci_high": null, "significant": false}}, "Kidney & Renal Pelvis": {"male": {"observed": 33.0, "expected": 33.8, "sir": 97.8, "ci_low": 67.3, "ci_high": 137.3, "significant": true}, "female": {"observed": 24.0, "expected": 19.7, "sir": 121.7, "ci_low": 77.9, "ci_high": 181.1, "significant": true}, "combined": {"observed": 57.0, "expected": 53.5, "sir": 106.54205607476635, "ci_low": null, "ci_high": null, "significant": true}}, "Stomach": {"male": {"observed": 17.0, "expected": 14.6, "sir": 116.6, "ci_low": 67.9, "ci_high": 186.7, "significant": true}, "female": {"observed": 8.0, "expected": 8.9, "sir": 89.8, "ci_low": 38.7, "ci_high": 177.0, "significant": true}, "combined": {"observed": 25.0, "expected": 23.5, "sir": 106.38297872340425, "ci_low": null, "ci_high": null, "significant": true}}, "Larynx": {"male": {"observed": 10.0, "expected": 8.9, "sir": 113.0, "ci_low": 54.1, "ci_high": 207.8, "significant": true}, "female": {"observed": 6.0, "expected": 2.7, "sir": 219.7, "ci_low": 80.2, "ci_high": 478.2, "significant": true}, "combined": {"observed": 16.0, "expected": 11.600000000000001, "sir": 137.9310344827586, "ci_low": null, "ci_high": null, "significant": true}}, "Testis": {"male": {"observed": 7.0, "expected": 9.5, "sir": 73.4, "ci_low": 29.4, "ci_high": 151.2, "significant": true}, "female": {"observed": 0, "expected": 0, "sir": null, "ci_low": null, "ci_high": null, "significant": false}, "combined": {"observed": 7.0, "expected": 9.5, "sir": null, "ci_low": null, "ci_high": null, "significant": false}}, "Leukemia": {"male": {"observed": 21.0, "expected": 25.1, "sir": 83.6, "ci_low": 51.7, "ci_high": 127.8, "significant": true}, "female": {"observed": 18.0, "expected": 18.7, "sir": 96.2, "ci_low": 57.0, "ci_high": 152.0, "significant": true}, "combined": {"observed": 39.0, "expected": 43.8, "sir": 89.04109589041096, "ci_low": null, "ci_high": null, "significant": true}}, "Thyroid": {"male": {"observed": 17.0, "expected": 16.0, "sir": 106.3, "ci_low": 61.9, "ci_high": 170.2, "significant": true}, "female": {"observed": 57.0, "expected": 49.2, "sir": 115.9, "ci_low": 87.8, "ci_high": 150.2, "significant": true}, "combined": {"observed": 74.0, "expected": 65.2, "sir": 113.4969325153374, "ci_low": null, "ci_high": null, "significant": true}}, "Liver and Intrahepatic Bile Ducts": {"male": {"observed": 17.0, "expected": 21.1, "sir": 80.7, "ci_low": 47.0, "ci_high": 129.2, "significant": true}, "female": {"observed": 6.0, "expected": 7.3, "sir": 82.7, "ci_low": 30.2, "ci_high": 180.0, "significant": true}, "combined": {"observed": 23.0, "expected": 28.400000000000002, "sir": 80.98591549295774, "ci_low": null, "ci_high": null, "significant": true}}, "Uteri Corpus and Uterus, NOS": {"male": {"observed": 0, "expected": 0, "sir": null, "ci_low": null, "ci_high": null, "significant": false}, "female": {"observed": 62.0, "expected": 55.8, "sir": 111.2, "ci_low": 85.3, "ci_high": 142.6, "significant": true}, "combined": {"observed": 62.0, "expected": 55.8, "sir": null, "ci_low": null, "ci_high": null, "significant": false}}, "Lung and Bronchus": {"male": {"observed": 105.0, "expected": 104.3, "sir": 100.6, "ci_low": 82.3, "ci_high": 121.8, "significant": true}, "female": {"observed": 138.0, "expected": 112.5, "sir": 122.7, "ci_low": 103.0, "ci_high": 144.9, "significant": true}, "combined": {"observed": 243.0, "expected": 216.8, "sir": 112.08487084870849, "ci_low": null, "ci_high": null, "significant": true}}, "All Sites / Types": {"male": {"observed": 711.0, "expected": 779.2, "sir": 91.2, "ci_low": 84.7, "ci_high": 98.2, "significant": true}, "female": {"observed": 888.0, "expected": 839.3, "sir": 105.8, "ci_low": 99.0, "ci_high": 113.0, "significant": true}, "combined": {"observed": 1599.0, "expected": 1618.5, "sir": 98.79518072289156, "ci_low": null, "ci_high": null, "significant": true}}}, "11-15": {"Bladder, Urinary": {"male": {"observed": 54.0, "expected": 61.0, "sir": 88.5, "ci_low": 66.5, "ci_high": 115.5, "significant": true}, "female": {"observed": 33.0, "expected": 21.5, "sir": 153.6, "ci_low": 105.7, "ci_high": 215.7, "significant": true}, "combined": {"observed": 87.0, "expected": 82.5, "sir": 105.45454545454544, "ci_low": null, "ci_high": null, "significant": true}}, "Melanoma of Skin": {"male": {"observed": 29.0, "expected": 39.9, "sir": 72.7, "ci_low": 48.7, "ci_high": 104.5, "significant": true}, "female": {"observed": 17.0, "expected": 32.2, "sir": 52.8, "ci_low": 30.7, "ci_high": 84.5, "significant": true}, "combined": {"observed": 46.0, "expected": 72.1, "sir": 63.80027739251041, "ci_low": null, "ci_high": null, "significant": true}}, "Brain and Other Nervous System": {"male": {"observed": 14.0, "expected": 12.1, "sir": 115.4, "ci_low": 63.0, "ci_high": 193.6, "significant": true}, "female": {"observed": 16.0, "expected": 10.5, "sir": 152.1, "ci_low": 86.9, "ci_high": 247.0, "significant": true}, "combined": {"observed": 30.0, "expected": 22.6, "sir": 132.7433628318584, "ci_low": null, "ci_high": null, "significant": true}}, "Multiple Myeloma": {"male": {"observed": 8.0, "expected": 12.6, "sir": 63.5, "ci_low": 27.3, "ci_high": 125.0, "significant": true}, "female": {"observed": 10.0, "expected": 10.2, "sir": 98.2, "ci_low": 47.0, "ci_high": 180.7, "significant": true}, "combined": {"observed": 18.0, "expected": 22.799999999999997, "sir": 78.94736842105264, "ci_low": null, "ci_high": null, "significant": true}}, "Breast": {"male": {"observed": 3.0, "expected": 2.1, "sir": null, "ci_low": null, "ci_high": null, "significant": false}, "female": {"observed": 242.0, "expected": 255.2, "sir": 94.8, "ci_low": 83.3, "ci_high": 107.6, "significant": true}, "combined": {"observed": 245.0, "expected": 257.3, "sir": null, "ci_low": null, "ci_high": null, "significant": false}}, "Non-Hodgkin Lymphoma": {"male": {"observed": 36.0, "expected": 35.6, "sir": 101.2, "ci_low": 70.9, "ci_high": 140.2, "significant": true}, "female": {"observed": 39.0, "expected": 30.4, "sir": 128.5, "ci_low": 91.4, "ci_high": 175.7, "significant": true}, "combined": {"observed": 75.0, "expected": 66.0, "sir": 113.63636363636364, "ci_low": null, "ci_high": null, "significant": true}}, "Cervix Uteri": {"male": {"observed": 0, "expected": 0, "sir": null, "ci_low": null, "ci_high": null, "significant": false}, "female": {"observed": 9.0, "expected": 8.8, "sir": 102.1, "ci_low": 46.6, "ci_high": 193.8, "significant": true}, "combined": {"observed": 9.0, "expected": 8.8, "sir": null, "ci_low": null, "ci_high": null, "significant": false}}, "Oral Cavity & Pharynx": {"male": {"observed": 27.0, "expected": 30.0, "sir": 90.0, "ci_low": 59.3, "ci_high": 131.0, "significant": true}, "female": {"observed": 12.0, "expected": 13.7, "sir": 87.7, "ci_low": 45.3, "ci_high": 153.3, "significant": true}, "combined": {"observed": 39.0, "expected": 43.7, "sir": 89.24485125858122, "ci_low": null, "ci_high": null, "significant": true}}, "Colon / Rectum": {"male": {"observed": 64.0, "expected": 65.9, "sir": 97.2, "ci_low": 74.8, "ci_high": 124.1, "significant": true}, "female": {"observed": 71.0, "expected": 63.5, "sir": 111.8, "ci_low": 87.3, "ci_high": 141.0, "significant": true}, "combined": {"observed": 135.0, "expected": 129.4, "sir": 104.3276661514683, "ci_low": null, "ci_high": null, "significant": true}}, "Ovary": {"male": {"observed": 0, "expected": 0, "sir": null, "ci_low": null, "ci_high": null, "significant": false}, "female": {"observed": 18.0, "expected": 22.0, "sir": 81.9, "ci_low": 48.5, "ci_high": 129.4, "significant": true}, "combined": {"observed": 18.0, "expected": 22.0, "sir": null, "ci_low": null, "ci_high": null, "significant": false}}, "Esophagus": {"male": {"observed": 13.0, "expected": 15.5, "sir": 84.1, "ci_low": 44.7, "ci_high": 143.8, "significant": true}, "female": {"observed": 8.0, "expected": 4.2, "sir": 188.9, "ci_low": 81.3, "ci_high": 372.3, "significant": true}, "combined": {"observed": 21.0, "expected": 19.7, "sir": 106.59898477157361, "ci_low": null, "ci_high": null, "significant": true}}, "Pancreas": {"male": {"observed": 23.0, "expected": 22.8, "sir": 101.1, "ci_low": 64.1, "ci_high": 151.7, "significant": true}, "female": {"observed": 28.0, "expected": 22.5, "sir": 124.2, "ci_low": 82.5, "ci_high": 179.6, "significant": true}, "combined": {"observed": 51.0, "expected": 45.3, "sir": 112.58278145695364, "ci_low": null, "ci_high": null, "significant": true}}, "Hodgkin Lymphoma": {"male": {"observed": 6.0, "expected": 5.0, "sir": 120.5, "ci_low": 44.0, "ci_high": 262.3, "significant": true}, "female": {"observed": 4.0, "expected": 4.3, "sir": null, "ci_low": null, "ci_high": null, "significant": false}, "combined": {"observed": 10.0, "expected": 9.3, "sir": null, "ci_low": null, "ci_high": null, "significant": false}}, "Prostate": {"male": {"observed": 156.0, "expected": 183.1, "sir": 85.2, "ci_low": 72.4, "ci_high": 99.7, "significant": true}, "female": {"observed": 0, "expected": 0, "sir": null, "ci_low": null, "ci_high": null, "significant": false}, "combined": {"observed": 156.0, "expected": 183.1, "sir": null, "ci_low": null, "ci_high": null, "significant": false}}, "Kidney & Renal Pelvis": {"male": {"observed": 36.0, "expected": 35.9, "sir": 100.2, "ci_low": 70.1, "ci_high": 138.7, "significant": true}, "female": {"observed": 23.0, "expected": 20.1, "sir": 114.4, "ci_low": 72.5, "ci_high": 171.7, "significant": true}, "combined": {"observed": 59.0, "expected": 56.0, "sir": 105.35714285714286, "ci_low": null, "ci_high": null, "significant": true}}, "Stomach": {"male": {"observed": 18.0, "expected": 14.5, "sir": 124.5, "ci_low": 73.7, "ci_high": 196.8, "significant": true}, "female": {"observed": 7.0, "expected": 8.9, "sir": 79.0, "ci_low": 31.7, "ci_high": 162.8, "significant": true}, "combined": {"observed": 25.0, "expected": 23.4, "sir": 106.83760683760684, "ci_low": null, "ci_high": null, "significant": true}}, "Larynx": {"male": {"observed": 12.0, "expected": 8.9, "sir": 134.4, "ci_low": 69.4, "ci_high": 234.7, "significant": true}, "female": {"observed": 5.0, "expected": 2.8, "sir": 179.0, "ci_low": 57.7, "ci_high": 417.8, "significant": true}, "combined": {"observed": 17.0, "expected": 11.7, "sir": 145.29914529914532, "ci_low": null, "ci_high": null, "significant": true}}, "Testis": {"male": {"observed": 7.0, "expected": 9.8, "sir": 71.3, "ci_low": 28.6, "ci_high": 146.9, "significant": true}, "female": {"observed": 0, "expected": 0, "sir": null, "ci_low": null, "ci_high": null, "significant": false}, "combined": {"observed": 7.0, "expected": 9.8, "sir": null, "ci_low": null, "ci_high": null, "significant": false}}, "Leukemia": {"male": {"observed": 22.0, "expected": 25.4, "sir": 86.8, "ci_low": 54.4, "ci_high": 131.4, "significant": true}, "female": {"observed": 22.0, "expected": 18.4, "sir": 119.6, "ci_low": 74.9, "ci_high": 181.1, "significant": true}, "combined": {"observed": 44.0, "expected": 43.8, "sir": 100.45662100456623, "ci_low": null, "ci_high": null, "significant": true}}, "Thyroid": {"male": {"observed": 16.0, "expected": 17.0, "sir": 94.3, "ci_low": 53.9, "ci_high": 153.2, "significant": true}, "female": {"observed": 61.0, "expected": 50.6, "sir": 120.5, "ci_low": 92.1, "ci_high": 154.8, "significant": true}, "combined": {"observed": 77.0, "expected": 67.6, "sir": 113.90532544378699, "ci_low": null, "ci_high": null, "significant": true}}, "Liver and Intrahepatic Bile Ducts": {"male": {"observed": 16.0, "expected": 22.2, "sir": 72.2, "ci_low": 41.3, "ci_high": 117.3, "significant": true}, "female": {"observed": 6.0, "expected": 7.4, "sir": 81.6, "ci_low": 29.8, "ci_high": 177.6, "significant": true}, "combined": {"observed": 22.0, "expected": 29.6, "sir": 74.32432432432432, "ci_low": null, "ci_high": null, "significant": true}}, "Uteri Corpus and Uterus, NOS": {"male": {"observed": 0, "expected": 0, "sir": null, "ci_low": null, "ci_high": null, "significant": false}, "female": {"observed": 69.0, "expected": 57.6, "sir": 119.8, "ci_low": 93.2, "ci_high": 151.6, "significant": true}, "combined": {"observed": 69.0, "expected": 57.6, "sir": null, "ci_low": null, "ci_high": null, "significant": false}}, "Lung and Bronchus": {"male": {"observed": 116.0, "expected": 104.3, "sir": 111.2, "ci_low": 91.9, "ci_high": 133.4, "significant": true}, "female": {"observed": 134.0, "expected": 112.5, "sir": 119.1, "ci_low": 99.8, "ci_high": 141.1, "significant": true}, "combined": {"observed": 250.0, "expected": 216.8, "sir": 115.31365313653137, "ci_low": null, "ci_high": null, "significant": true}}, "All Sites / Types": {"male": {"observed": 723.0, "expected": 787.2, "sir": 91.8, "ci_low": 85.3, "ci_high": 98.8, "significant": true}, "female": {"observed": 895.0, "expected": 843.6, "sir": 106.1, "ci_low": 99.2, "ci_high": 113.3, "significant": true}, "combined": {"observed": 1618.0, "expected": 1630.8000000000002, "sir": 99.21510914888397, "ci_low": null, "ci_high": null, "significant": true}}}, "Average": {"Bladder, Urinary": {"male": {"observed": 56.0, "expected": 58.85, "sir": 95.1571792693288, "significant": 1}, "female": {"observed": 29.0, "expected": 21.8, "sir": 133.0275229357798, "significant": 1}, "combined": {"observed": 85.0, "expected": 80.65, "sir": 105.39367637941723, "significant": 1}}, "Melanoma of Skin": {"male": {"observed": 29.25, "expected": 38.675, "sir": 75.63025210084035, "significant": 1}, "female": {"observed": 20.75, "expected": 32.425, "sir": 63.99383191981496, "significant": 1}, "combined": {"observed": 50.0, "expected": 71.1, "sir": 70.32348804500704, "significant": 1}}, "Brain and Other Nervous System": {"male": {"observed": 14.0, "expected": 11.950000000000001, "sir": 117.15481171548117, "significant": 1}, "female": {"observed": 12.25, "expected": 10.3, "sir": 118.93203883495144, "significant": 1}, "combined": {"observed": 26.25, "expected": 22.25, "sir": 117.97752808988764, "significant": 1}}, "Multiple Myeloma": {"male": {"observed": 9.25, "expected": 11.875000000000002, "sir": 77.89473684210525, "significant": 1}, "female": {"observed": 8.25, "expected": 9.899999999999999, "sir": 83.33333333333334, "significant": 1}, "combined": {"observed": 17.5, "expected": 21.775000000000002, "sir": 80.36739380022962, "significant": 1}}, "Breast": {"male": {"observed": 2.0, "expected": 2.0, "sir": null, "significant": 0}, "female": {"observed": 249.0, "expected": 249.35000000000002, "sir": 99.85963505113293, "significant": 1}, "combined": {"observed": 251.0, "expected": 251.35000000000002, "sir": null, "significant": 0}}, "Non-Hodgkin Lymphoma": {"male": {"observed": 37.25, "expected": 34.675, "sir": 107.42609949531364, "significant": 1}, "female": {"observed": 41.5, "expected": 30.625, "sir": 135.51020408163265, "significant": 1}, "combined": {"observed": 78.75, "expected": 65.3, "sir": 120.59724349157734, "significant": 1}}, "Cervix Uteri": {"male": {"observed": 0.0, "expected": 0.0, "sir": null, "significant": 0}, "female": {"observed": 6.75, "expected": 8.925, "sir": null, "significant": 0}, "combined": {"observed": 6.75, "expected": 8.925, "sir": null, "significant": 0}}, "Oral Cavity & Pharynx": {"male": {"observed": 34.0, "expected": 28.475, "sir": 119.40298507462686, "significant": 1}, "female": {"observed": 15.0, "expected": 13.125, "sir": 114.28571428571428, "significant": 1}, "combined": {"observed": 49.0, "expected": 41.6, "sir": 117.78846153846155, "significant": 1}}, "Colon / Rectum": {"male": {"observed": 72.5, "expected": 65.25, "sir": 111.11111111111111, "significant": 1}, "female": {"observed": 71.0, "expected": 66.55, "sir": 106.68670172802403, "significant": 1}, "combined": {"observed": 143.5, "expected": 131.8, "sir": 108.87708649468892, "significant": 1}}, "Ovary": {"male": {"observed": 0.0, "expected": 0.0, "sir": null, "significant": 0}, "female": {"observed": 20.25, "expected": 22.05, "sir": 91.83673469387756, "significant": 1}, "combined": {"observed": 20.25, "expected": 22.05, "sir": null, "significant": 0}}, "Esophagus": {"male": {"observed": 12.5, "expected": 15.325, "sir": 81.56606851549756, "significant": 1}, "female": {"observed": 5.25, "expected": 4.225, "sir": null, "significant": 0}, "combined": {"observed": 17.75, "expected": 19.55, "sir": null, "significant": 0}}, "Pancreas": {"male": {"observed": 25.0, "expected": 21.05, "sir": 118.76484560570071, "significant": 1}, "female": {"observed": 27.5, "expected": 22.2, "sir": 123.87387387387388, "significant": 1}, "combined": {"observed": 52.5, "expected": 43.25, "sir": 121.38728323699422, "significant": 1}}, "Hodgkin Lymphoma": {"male": {"observed": 6.25, "expected": 5.025, "sir": 124.37810945273631, "significant": 1}, "female": {"observed": 3.5, "expected": 4.2, "sir": null, "significant": 0}, "combined": {"observed": 9.75, "expected": 9.225000000000001, "sir": null, "significant": 0}}, "Prostate": {"male": {"observed": 161.0, "expected": 190.70000000000002, "sir": 84.42579968536968, "significant": 1}, "female": {"observed": 0.0, "expected": 0.0, "sir": null, "significant": 0}, "combined": {"observed": 161.0, "expected": 190.70000000000002, "sir": null, "significant": 0}}, "Kidney & Renal Pelvis": {"male": {"observed": 34.5, "expected": 33.525, "sir": 102.9082774049217, "significant": 1}, "female": {"observed": 23.5, "expected": 19.625, "sir": 119.7452229299363, "significant": 1}, "combined": {"observed": 58.0, "expected": 53.15, "sir": 109.12511759172155, "significant": 1}}, "Stomach": {"male": {"observed": 19.0, "expected": 14.075, "sir": 134.9911190053286, "significant": 1}, "female": {"observed": 7.25, "expected": 8.799999999999999, "sir": 82.38636363636364, "significant": 1}, "combined": {"observed": 26.25, "expected": 22.875, "sir": 114.75409836065573, "significant": 1}}, "Larynx": {"male": {"observed": 10.0, "expected": 8.799999999999999, "sir": 113.63636363636364, "significant": 1}, "female": {"observed": 4.75, "expected": 2.8, "sir": null, "significant": 0}, "combined": {"observed": 14.75, "expected": 11.600000000000001, "sir": null, "significant": 0}}, "Testis": {"male": {"observed": 7.5, "expected": 9.524999999999999, "sir": 78.74015748031498, "significant": 1}, "female": {"observed": 0.0, "expected": 0.0, "sir": null, "significant": 0}, "combined": {"observed": 7.5, "expected": 9.524999999999999, "sir": null, "significant": 0}}, "Leukemia": {"male": {"observed": 21.25, "expected": 24.550000000000004, "sir": 86.5580448065173, "significant": 1}, "female": {"observed": 19.5, "expected": 18.549999999999997, "sir": 105.12129380053909, "significant": 1}, "combined": {"observed": 40.75, "expected": 43.10000000000001, "sir": 94.54756380510439, "significant": 1}}, "Thyroid": {"male": {"observed": 16.0, "expected": 16.025, "sir": 99.84399375975039, "significant": 1}, "female": {"observed": 55.5, "expected": 49.37499999999999, "sir": 112.40506329113926, "significant": 1}, "combined": {"observed": 71.5, "expected": 65.4, "sir": 109.32721712538225, "significant": 1}}, "Liver and Intrahepatic Bile Ducts": {"male": {"observed": 17.25, "expected": 20.875, "sir": 82.63473053892216, "significant": 1}, "female": {"observed": 5.0, "expected": 7.075000000000001, "sir": null, "significant": 0}, "combined": {"observed": 22.25, "expected": 27.950000000000003, "sir": null, "significant": 0}}, "Uteri Corpus and Uterus, NOS": {"male": {"observed": 0.0, "expected": 0.0, "sir": null, "significant": 0}, "female": {"observed": 62.5, "expected": 55.925, "sir": 111.75681716584714, "significant": 1}, "combined": {"observed": 62.5, "expected": 55.925, "sir": null, "significant": 0}}, "Lung and Bronchus": {"male": {"observed": 108.0, "expected": 102.9, "sir": 104.95626822157433, "significant": 1}, "female": {"observed": 142.25, "expected": 112.1, "sir": 126.8956289027654, "significant": 1}, "combined": {"observed": 250.25, "expected": 215.0, "sir": 116.3953488372093, "significant": 1}}, "All Sites / Types": {"male": {"observed": 742.0, "expected": 776.3, "sir": 95.58160504959423, "significant": 1}, "female": {"observed": 896.75, "expected": 837.2499999999999, "sir": 107.1065989847716, "significant": 1}, "combined": {"observed": 1638.75, "expected": 1613.55, "sir": 101.56177372873478, "significant": 1}}}, "Rank": {"08-12": {"All Sites / Types": {"male": 258, "female": 276, "combined": 277}}, "09-13": {"All Sites / Types": {"male": 172, "female": 266, "combined": 236}}, "10-14": {"All Sites / Types": {"male": 136, "female": 247, "combined": 197}}, "11-15": {"All Sites / Types": {"male": 150, "female": 267, "combined": 211}}, "Average": {"All Sites / Types": {"male": 172, "female": 274, "combined": 240}}}}