{"Bladder, Urinary": {"male": {"observed": 18.0, "expected": 21.3, "sir": 84.6, "ci_low": 50.1, "ci_high": 133.7, "significant": true}, "female": {"observed": 10.0, "expected": 7.0, "sir": 142.2, "ci_low": 68.1, "ci_high": 261.5, "significant": true}, "combined": {"observed": 28.0, "expected": 28.3, "sir": 98.9399293286219, "ci_low": null, "ci_high": null, "significant": true}}, "Melanoma of Skin": {"male": {"observed": 16.0, "expected": 12.7, "sir": 125.9, "ci_low": 71.9, "ci_high": 204.5, "significant": true}, "female": {"observed": 9.0, "expected": 8.9, "sir": 101.1, "ci_low": 46.2, "ci_high": 192.0, "significant": true}, "combined": {"observed": 25.0, "expected": 21.6, "sir": 115.74074074074075, "ci_low": null, "ci_high": null, "significant": true}}, "Brain and Other Nervous System": {"male": {"observed": 3.0, "expected": 3.5, "sir": null, "ci_low": null, "ci_high": null, "significant": false}, "female": {"observed": 7.0, "expected": 2.8, "sir": 247.5, "ci_low": 99.2, "ci_high": 510.0, "significant": true}, "combined": {"observed": 10.0, "expected": 6.3, "sir": null, "ci_low": null, "ci_high": null, "significant": false}}, "Multiple Myeloma": {"male": {"observed": 4.0, "expected": 4.2, "sir": null, "ci_low": null, "ci_high": null, "significant": false}, "female": {"observed": 2.0, "expected": 3.2, "sir": null, "ci_low": null, "ci_high": null, "significant": false}, "combined": {"observed": 6.0, "expected": 7.4, "sir": null, "ci_low": null, "ci_high": null, "significant": false}}, "Breast": {"male": {"observed": 0.0, "expected": 0.7, "sir": null, "ci_low": null, "ci_high": null, "significant": false}, "female": {"observed": 80.0, "expected": 74.0, "sir": 108.1, "ci_low": 85.7, "ci_high": 134.6, "significant": true}, "combined": {"observed": 80.0, "expected": 74.7, "sir": null, "ci_low": null, "ci_high": null, "significant": false}}, "Non-Hodgkin Lymphoma": {"male": {"observed": 9.0, "expected": 11.5, "sir": 78.4, "ci_low": 35.8, "ci_high": 148.8, "significant": true}, "female": {"observed": 11.0, "expected": 9.5, "sir": 115.4, "ci_low": 57.5, "ci_high": 206.5, "significant": true}, "combined": {"observed": 20.0, "expected": 21.0, "sir": 95.23809523809523, "ci_low": null, "ci_high": null, "significant": true}}, "Cervix Uteri": {"male": {"observed": 0, "expected": 0, "sir": null, "ci_low": null, "ci_high": null, "significant": false}, "female": {"observed": 1.0, "expected": 2.2, "sir": null, "ci_low": null, "ci_high": null, "significant": false}, "combined": {"observed": 1.0, "expected": 2.2, "sir": null, "ci_low": null, "ci_high": null, "significant": false}}, "Oral Cavity & Pharynx": {"male": {"observed": 8.0, "expected": 9.3, "sir": 85.6, "ci_low": 36.9, "ci_high": 168.7, "significant": true}, "female": {"observed": 2.0, "expected": 4.0, "sir": null, "ci_low": null, "ci_high": null, "significant": false}, "combined": {"observed": 10.0, "expected": 13.3, "sir": null, "ci_low": null, "ci_high": null, "significant": false}}, "Colon / Rectum": {"male": {"observed": 21.0, "expected": 22.1, "sir": 95.0, "ci_low": 58.8, "ci_high": 145.3, "significant": true}, "female": {"observed": 15.0, "expected": 20.7, "sir": 72.4, "ci_low": 40.5, "ci_high": 119.5, "significant": true}, "combined": {"observed": 36.0, "expected": 42.8, "sir": 84.11214953271029, "ci_low": null, "ci_high": null, "significant": true}}, "Ovary": {"male": {"observed": 0, "expected": 0, "sir": null, "ci_low": null, "ci_high": null, "significant": false}, "female": {"observed": 8.0, "expected": 6.4, "sir": 125.1, "ci_low": 53.9, "ci_high": 246.4, "significant": true}, "combined": {"observed": 8.0, "expected": 6.4, "sir": null, "ci_low": null, "ci_high": null, "significant": false}}, "Esophagus": {"male": {"observed": 2.0, "expected": 5.3, "sir": null, "ci_low": null, "ci_high": null, "significant": false}, "female": {"observed": 4.0, "expected": 1.4, "sir": null, "ci_low": null, "ci_high": null, "significant": false}, "combined": {"observed": 6.0, "expected": 6.699999999999999, "sir": null, "ci_low": null, "ci_high": null, "significant": false}}, "Pancreas": {"male": {"observed": 3.0, "expected": 7.5, "sir": null, "ci_low": null, "ci_high": null, "significant": false}, "female": {"observed": 10.0, "expected": 7.3, "sir": 136.4, "ci_low": 65.3, "ci_high": 250.8, "significant": true}, "combined": {"observed": 13.0, "expected": 14.8, "sir": null, "ci_low": null, "ci_high": null, "significant": false}}, "Hodgkin Lymphoma": {"male": {"observed": 1.0, "expected": 1.2, "sir": null, "ci_low": null, "ci_high": null, "significant": false}, "female": {"observed": 1.0, "expected": 0.9, "sir": null, "ci_low": null, "ci_high": null, "significant": false}, "combined": {"observed": 2.0, "expected": 2.1, "sir": null, "ci_low": null, "ci_high": null, "significant": false}}, "Prostate": {"male": {"observed": 45.0, "expected": 65.1, "sir": 69.2, "ci_low": 50.4, "ci_high": 92.5, "significant": true}, "female": {"observed": 0, "expected": 0, "sir": null, "ci_low": null, "ci_high": null, "significant": false}, "combined": {"observed": 45.0, "expected": 65.1, "sir": null, "ci_low": null, "ci_high": null, "significant": false}}, "Kidney & Renal Pelvis": {"male": {"observed": 10.0, "expected": 11.0, "sir": 91.2, "ci_low": 43.6, "ci_high": 167.7, "significant": true}, "female": {"observed": 4.0, "expected": 5.9, "sir": null, "ci_low": null, "ci_high": null, "significant": false}, "combined": {"observed": 14.0, "expected": 16.9, "sir": null, "ci_low": null, "ci_high": null, "significant": false}}, "Stomach": {"male": {"observed": 5.0, "expected": 5.0, "sir": 100.2, "ci_low": 32.3, "ci_high": 233.9, "significant": true}, "female": {"observed": 3.0, "expected": 2.8, "sir": null, "ci_low": null, "ci_high": null, "significant": false}, "combined": {"observed": 8.0, "expected": 7.8, "sir": null, "ci_low": null, "ci_high": null, "significant": false}}, "Larynx": {"male": {"observed": 2.0, "expected": 3.0, "sir": null, "ci_low": null, "ci_high": null, "significant": false}, "female": {"observed": 1.0, "expected": 0.8, "sir": null, "ci_low": null, "ci_high": null, "significant": false}, "combined": {"observed": 3.0, "expected": 3.8, "sir": null, "ci_low": null, "ci_high": null, "significant": false}}, "Testis": {"male": {"observed": 1.0, "expected": 1.8, "sir": null, "ci_low": null, "ci_high": null, "significant": false}, "female": {"observed": 0, "expected": 0, "sir": null, "ci_low": null, "ci_high": null, "significant": false}, "combined": {"observed": 1.0, "expected": 1.8, "sir": null, "ci_low": null, "ci_high": null, "significant": false}}, "Leukemia": {"male": {"observed": 3.0, "expected": 8.1, "sir": null, "ci_low": null, "ci_high": null, "significant": false}, "female": {"observed": 7.0, "expected": 5.5, "sir": 128.0, "ci_low": 51.3, "ci_high": 263.8, "significant": true}, "combined": {"observed": 10.0, "expected": 13.6, "sir": null, "ci_low": null, "ci_high": null, "significant": false}}, "Thyroid": {"male": {"observed": 4.0, "expected": 4.5, "sir": null, "ci_low": null, "ci_high": null, "significant": false}, "female": {"observed": 10.0, "expected": 11.8, "sir": 84.8, "ci_low": 40.6, "ci_high": 156.0, "significant": true}, "combined": {"observed": 14.0, "expected": 16.3, "sir": null, "ci_low": null, "ci_high": null, "significant": false}}, "Liver and Intrahepatic Bile Ducts": {"male": {"observed": 7.0, "expected": 6.9, "sir": 100.8, "ci_low": 40.4, "ci_high": 207.7, "significant": true}, "female": {"observed": 2.0, "expected": 2.2, "sir": null, "ci_low": null, "ci_high": null, "significant": false}, "combined": {"observed": 9.0, "expected": 9.100000000000001, "sir": null, "ci_low": null, "ci_high": null, "significant": false}}, "Uteri Corpus and Uterus, NOS": {"male": {"observed": 0, "expected": 0, "sir": null, "ci_low": null, "ci_high": null, "significant": false}, "female": {"observed": 12.0, "expected": 16.5, "sir": 72.8, "ci_low": 37.5, "ci_high": 127.1, "significant": true}, "combined": {"observed": 12.0, "expected": 16.5, "sir": null, "ci_low": null, "ci_high": null, "significant": false}}, "Lung and Bronchus": {"male": {"observed": 25.0, "expected": 37.2, "sir": 67.1, "ci_low": 43.4, "ci_high": 99.1, "significant": true}, "female": {"observed": 24.0, "expected": 35.7, "sir": 67.2, "ci_low": 43.0, "ci_high": 100.0, "significant": true}, "combined": {"observed": 49.0, "expected": 72.9, "sir": 67.2153635116598, "ci_low": null, "ci_high": null, "significant": true}}, "All Sites / Types": {"male": {"observed": 207.0, "expected": 263.2, "sir": 78.7, "ci_low": 68.3, "ci_high": 90.1, "significant": true}, "female": {"observed": 241.0, "expected": 250.8, "sir": 96.1, "ci_low": 84.3, "ci_high": 109.0, "significant": true}, "combined": {"observed": 448.0, "expected": 514.0, "sir": 87.15953307392996, "ci_low": null, "ci_high": null, "significant": true}}}